Workbook

Sheet 1.1) Рег. уровень_безопис
A1: Страна | B1: Год | C1: Дата | D1: Состав | E1: Лидер | F1: Тип события | G1: Место проведения | H1: Текст | I1: Ссылка | J1: Кол-во упоминаний | K1: Кол-во_ сюжет_транспортно_логистический | L1: Кол-во_ сюжет_экономический | M1: Кол-во_сюжет_геополитический | N1: Кол-во_Сюжет_цивилизационный | O1: Кол-во_сюжет_институциональный | P1: Кол-во_сюжет_социально_гуманитарный
J2: евразий- | K2: "автомобильный транспорт", "железнодорожный транспорт", "авиасообщение", "морской транспорт", "мультимодальный транспорт", "транспортная инфраструктура", "железная дорога", "пункт пропуска", "логистика", "грузоперевозки", "транзит", "транзитный потенциал", "грузооборот", "контейнерные перевозки", "связанность", "транспортная связанность", "единое транспортное пространство", "транспортный коридор", "шёлковый путь", "шелковый путь", "север-юг", "транспортный маршрут", "транспортные тарифы", "либерализация перевозок", "цифровая логистика", "умная граница", "навигационные пломбы", "логистический хаб", "сухой порт", "контейнерный терминал" | L2: "рынок", "общий рынок", "единый рынок", "ёмкий рынок", "торговля", "товарооборот", "экспорт", "импорт", "поставки", "инвестиции", "инвесторы", "капитал", "капиталовложения", "ввп", "экономический рост", "рост экономики", "развитие экономики", "конкурентоспособность", "барьеры", "ограничения", "пошлины", "тарифы", "нетарифные барьеры", "производительность", "добавленная стоимость", "промышленность", "отрасли", "бизнес", "предприниматели", "компании", "предприятия", "интеграция рынков", "экономическая интеграция", "экономический союз" | M2: "центр силы", "полюс", "полюс роста", "центр мирового", "центр регионального", "многополярный мир", "многополярность", "суверенитет", "независимость", "стратегическая автономия", "геополитика", "геополитический", "геополитические интересы", "стратегические интересы", "мировой порядок", "международная система", "архитектура безопасности", "влияние", "лидерство", "позиционирование", "роль в мире", "баланс", "противостояние" | N2: "цивилизация", "цивилизационный", "евразийская цивилизация", "общая история", "историческое единство", "исторические корни", "наследие", "культура", "культурные традиции", "духовные ценности", "духовность", "идентичность", "общая идентичность", "общность", "традиционные ценности", "общие ценности", "менталитет", "особый путь", "свой путь развития", "путь наших народов", "братские народы", "многовековые связи", "историческое братство" | O2: "договор", "соглашение", "ратификация", "ратифицирован", "протокол", "решение", "документ", "орган", "комиссия", "совет", "комитет", "рабочая группа", "институт", "институты союза", "регламент", "процедура", "механизм", "инструменты", "нормативная база", "дорожная карта", "дорожные карты", "программа", "план мероприятий", "компетенции", "полномочия", "юрисдикция", "порядок председательства", "распределение голосов", "структура органов", "правовая база", "договорно-правовая база", "договорно‑правовая база", "юрисдикция суда" | P2: "граждане", "наши граждане", "люди", "население", "трудовая миграция", "мигранты", "условия труда", "социальные гарантии", "образование", "университеты", "студенты", "академические обмены", "наука", "научное сотрудничество", "исследования", "культура", "культурные обмены", "язык", "гуманитарные проекты", "здравоохранение", "медицина", "фармацевтика", "социальная защита", "пенсии", "социальные выплаты", "уровень жизни", "качество жизни", "молодежь", "молодёжные программы", "молодежные программы", "студенческие программы"
A4: Россия | B4: 2014 | C4: 23 декабря | E4: Путин | F4: заседание ВЕЭС | G4: Москва | H4: В.Путин: Уважаемые коллеги, добрый день! Мы проводим заключительное в этом году заседание Высшего Евразийского экономического совета. В углублении интеграции достигнуты хорошие, масштабные результаты. В сжатые сроки завершена подготовка Договора о создании Евразийского экономического союза. Мы подписали его в мае на саммите в Астане, а уже к нашей встрече в октябре в Минске Договор был ратифицирован парламентами России, Белоруссии и Казахстана и вступит в действие с 1 января 2015 года. Таким образом, Евразийский экономический союз заработает в полную силу. Как мы уже неоднократно говорили, будет создан общий ёмкий рынок с более чем 170 миллионами потребителей, обеспечена свобода передвижения товаров, услуг, капитала и рабочей силы. Бизнес получит возможность вести дела по универсальным прозрачным правилам международной торговли, основанным в том числе на принципах Всемирной торговой организации. Взаимная выгода от участия в интеграционных процессах очевидна. Успешная деятельность Таможенного союза, который мы создали в 2011 году, наглядно это подтвердила. Экономические связи внутри «тройки» укрепились и количественно, и качественно. Товарооборот вырос на 50 процентов. Что касается качества, то улучшилась структура взаимной торговли – за счёт повышения доли товаров с высокой добавленной стоимостью. Начало функционирования Евразийского союза означает переход на более продвинутый этап интеграции. Убеждён, это придаст дополнительный импульс развитию экономик наших государств. Союз станет мощным центром роста всего региона, увеличатся торговые и инвестиционные потоки, будут укрепляться деловые связи и повысится благосостояние наших граждан. Реализуемый нами интеграционный проект уникален не только по масштабу и содержанию, но и по духу. Он основан на принципах равноправия, доверия, взаимного уважения и учёта интересов друг друга. При этом его участники не отказываются от государственного суверенитета и сохраняют свою национальную самобытность. Мы стремимся находить взаимоприемлемые развязки и компромиссы по самым различным вопросам, руководствуемся принципом консенсуса при принятии основополагающих решений. Наши страны в равной степени представлены в руководящих органах и Суде Союза. Всё это делает евразийскую интеграцию привлекательной для соседей и партнёров по СНГ. Два месяца назад в Минске мы заключили Договор о присоединении к Союзу Армении. Процедуры его ратификации завершены, так что со 2 января будущего года Армения станет полноценным членом нашего объединения. С 1 января 2015 года Евразийский экономический союз заработает в полную силу. Будет создан общий ёмкий рынок, обеспечена свобода передвижения товаров, услуг, капитала и рабочей силы. Бизнес получит возможность вести дела по универсальным правилам международной торговли. Сегодня подпишем Договор о вступлении в Евразийский союз Киргизии. Киргизские друзья совместно с правительствами «тройки», Евразийской комиссией прилагают серьёзные усилия для адаптации национального законодательства к требованиям Таможенного союза и Единого экономического пространства. Реализована большая часть соответствующих дорожных карт. Важно не снижать темпов и сообща завершить эту работу. Интерес к наращиванию сотрудничества с Евразийским союзом проявляют и страны из других регионов. В финальную стадию вступила подготовка проекта соглашения о свободной торговле с Вьетнамом. Аналогичные договорённости прорабатываются с Турцией, Индией, Израилем. Совсем недавно, я коллегам сейчас об этом рассказывал, в ходе поездки в Узбекистан договорились с Президентом Узбекистана о том, что начнём работу, создадим рабочую группу по работе над договором о зоне свободной торговли между нашим объединением и Узбекистаном. Готовятся меморандумы о взаимопонимании с АСЕАН и МЕРКОСУР. Уверен, интересам нашего объединения одинаково отвечает расширение связей со всеми странами и организациями как на Востоке, так и на Западе – на основе равноправия и взаимной выгоды. Суммируя, хочу подчеркнуть, что наше интеграционное взаимодействие успешно развивается, налицо его конкретные осязаемые результаты. Однако останавливаться на достигнутом, конечно, нельзя, впереди новые большие задачи. Предстоит на практике наладить стабильное и эффективное функционирование Евразийского союза, продолжить работу по укреплению его институциональных основ. Ряд важных решений в этом направлении мы примем уже сегодня. В их числе договорённость о порядке председательства в нашем объединении. Среди других приоритетов вижу необходимость повышения конкурентоспособности и инвестиционной привлекательности Евразийского союза, запуск перспективных совместных проектов и создание высокотехнологичных рабочих мест в нефтегазовом комплексе, металлургии, химической промышленности, авиа- и машиностроении, космической отрасли. Нужно снимать остающиеся барьеры, ограничивающие свободу передвижения товаров, услуг, капиталов, рабочей силы. Предстоит реализовать планы по формированию с 2016 года общего рынка фармацевтической и медицинской продукции. Шагом к этому станет сегодняшнее наше решение об обороте лекарственных средств и медицинских изделий. Мы также утвердим перечень секторов услуг, в которых единый рынок начнёт функционировать уже с 1 января 2015 года. От этого выиграют строители, предприятия оптовой и розничной торговли, туристического бизнеса. Важно также не затягивать с взаимным признанием лицензий на ведение этих видов деятельности наших стран, чтобы наши компании уже с первых дней работы Союза могли в полной мере воспользоваться преимуществами интеграции. Рассчитываю, что наше заседание по традиции пройдёт в деловой и конструктивной атмосфере. Благодарю вас за внимание. | I4: http://www.kremlin.ru/events/president/transcripts/47311 | J4: 11 | K4: 0 | L4: 19 | M4: 1 | N4: 0 | O4: 14 | P4: 0
A5: Россия | B5: 2014 | C5: 10 октября | E5: Путин | F5: заседание ВЕЭС | G5: Минск | H5: В.ПУТИН: Уважаемые коллеги! Россия, Белоруссия и Казахстан уверенно идут по пути углубления евразийской интеграции. Парламенты наших стран к встрече в Минске синхронно ратифицировали Договор о Евразийском экономическом союзе. Как и договаривались, Евразийский экономический союз заработает с 1 января 2015 года. Мы переходим на новую, более высокую ступень интеграции, что позволит эффективнее решать задачи модернизации экономик наших стран и повышения их конкурентоспособности. Будет проводиться согласованная политика в ключевых отраслях промышленности, энергетики и сельского хозяйства, будут устранены барьеры, ограничивающие свободу передвижения товаров, услуг, капитала, рабочей силы. Создаваемый общий евразийский рынок начнёт функционировать по универсальным, прозрачным и понятным правилам, основанным на нормах и принципах Всемирной торговой организации. Отмечу, наш интеграционный проект уже приносит практическую отдачу. В рамках Таможенного союза с 1 июля 2011 года товарооборот вырос на 50 процентов, превысив отметку в 64 миллиарда долларов. Улучшилась структура взаимной торговли: продукция с высокой степенью переработки стала постепенно замещать сырьевые товары, [её доля] увеличилась существенным образом, а сырьевых товаров – снизилась с 40 до 28,9 процента. Весьма важно, что курс на тесную интеграцию пользуется широкой общественной поддержкой в наших странах. По данным социологических опросов, которые проведены Евразийским банком развития, деятельность Таможенного союза положительно оценивается 79 процентами граждан Российской Федерации, 68 процентами граждан Белоруссии и 84 процентами граждан Казахстана. Столь высокий уровень доверия необходимо оправдать достижением ощутимых результатов, а именно дальнейшим повышением качества жизни и благополучия населения наших стран. Уважаемые коллеги, в ходе нынешнего заседания мы подпишем Договор о присоединении Армении к Евразийскому экономическому союзу. Рассчитываем, что законодатели наших государств также слаженно одобрят его до конца года. На наш взгляд, Армения готова к работе в Евразийском экономическом союзе на равных с Россией, Белоруссией и Казахстаном. За относительно короткий срок, с осени 2013 года, наши армянские друзья подтянули экономическое регулирование под общие стандарты, привели национальное законодательство в соответствие с нормами нашего интеграционного объединения. Надеемся, что уже в первые год-два после присоединения Армении мы увидим положительный макроэкономический эффект. Товарооборот «тройки» с Арменией и так рос высокими темпами, прибавляя до 10 процентов ежегодно. После снятия таможенных и административных барьеров такая позитивная тенденция, надеюсь, ещё больше укрепится. Должны улучшиться и другие ключевые индикаторы: валовой продукт, потребительский спрос, реальные доходы населения и занятость. Сегодня предстоит также утвердить дорожную карту интеграции Киргизии в Единое экономическое пространство. Она позволит дополнить принятый ранее, на майском саммите в Астане, план по адаптации киргизской экономики к стандартам Таможенного союза. Мы понимаем, что киргизским коллегам необходимо содействие как в совершенствовании внутреннего законодательства, так и в проведении структурных преобразований. Россия такую помощь уже оказывает в рамках двусторонних договорённостей. Рассчитываем, что мы сможем объединить наши усилия с белорусскими и казахстанскими партнёрами. Помимо Армении и Киргизии интерес к сотрудничеству с Евразийским экономическим союзом проявляют и другие государства и региональные организации. В Евразийскую экономическую комиссию уже поступило несколько десятков предложений об установлении преференциальных режимов торговли. Этим так называемым внешним досье, как представляется, следует заниматься более активно. В частности, важно как можно скорее завершить переговоры по проекту соглашения о зоне свободной торговли с Вьетнамом, интенсифицировать экспертные консультации с Израилем, Индией, Египтом, продолжить развивать диалог с Южноамериканским общим рынком (МЕРКОСУР), Ассоциацией государств Юго-Восточной Азии (АСЕАН). Отдельно хочу сказать об отношениях с нашим соседом, Украиной, в контексте подписанного ею Соглашения об ассоциации с ЕС. В августе здесь, в Минске, главы государств «тройки» встретились с украинским Президентом и представителями Евросоюза. И Киев, и Брюссель прислушались к нашим аргументам, приняли решение отсрочить применение экономического блока Соглашения об ассоциации до 31 декабря 2015 года. Теперь появилась возможность откорректировать те положения упомянутого Соглашения, реализация которых могла бы нанести существенный ущерб экономике Таможенного союза и нашим традиционным торговым связям с Украиной. Конечно, переговоры предстоят непростые, и нам необходимо выступать с солидарных позиций, чтобы убедить партнёров отказаться от противопоставления европейской и евразийской интеграции в пользу сопряжения обоих проектов. Уважаемые коллеги! Хотел бы вновь подчеркнуть, что значение евразийской интеграции в жизни наших государств объективно возрастает. Это требует от всех нас ещё более слаженных и скоординированных действий, важно не снижать набранного темпа работы. До конца года нам необходимо утвердить ещё около пятидесяти документов по некоторым организационным и финансовым вопросам деятельности Евразийского экономического союза. Предлагаю, уважаемые коллеги, провести следующее наше заседание в декабре в Москве, где мы могли бы завершить весь подготовительный процесс. Мы уже и с Нурсултаном Абишевичем Назарбаевым, и с Президентом Белоруссии Александром Григорьевичем Лукашенко об этом говорили, я хотел бы об этом сказать здесь официально, на нашей встрече. И хочу вас поблагодарить за внимание. Спасибо большое. | I5: https://kazakhstan.mid.ru/ru/press-centre/news/vstrecha_glav_gosudarstv_vysshego_evraziyskogo_ekonomicheskogo_soveta/ | J5: 12 | K5: 0 | L5: 6 | M5: 0 | N5: 0 | O5: 8 | P5: 0
A6: Россия | B6: 2014 | C6: 5 марта | E6: Путин | F6: заседание ВЕЭС | G6: Московская область | H6: В.ПУТИН: Добрый день, уважаемые друзья, коллеги! Россия, Белоруссия и Казахстан последовательно продвигаются по пути интеграции, и сегодня мы в рамках Высшего Евразийского экономического совета на уровне глав государств поговорим о том, что происходит в этой сфере, куда мы двигаемся, каким темпом, выполняем ли мы все запланированные ранее шаги, все планы. Наша общая цель – перейти на новый, более высокий уровень взаимодействия и создать в начале 2015 года, как мы договаривались, Евразийский экономический союз. Для этого необходимо выдержать намеченные сроки и завершить к маю подготовку проекта договора. В соответствии с поручением, которое мы дали на предыдущем заседании в Москве (оно состоялось в декабре), правительства «тройки», Евразийская экономическая комиссия ускорили работу над текстом договора, он в деталях обсуждался и вчера в Астане на уровне вице-премьеров. Наш участник, это первый вице-премьер российского Правительства Игорь Шувалов, сегодня мне с утра уже докладывал об этих результатах. Институциональная часть договоров должна определить международно-правовой статус и организационные рамки будущего союза, закрепить основные принципы его деятельности. Функциональная, отраслевая часть будет регламентировать механизмы экономического взаимодействия. При этом важно гарантировать так называемые четыре свободы, то есть по обеспечению беспрепятственного перемещения товаров, услуг, капиталов и рабочей силы, зафиксировать конкретные обязательства по устранению изъятий и ограничений, сохраняющихся в Таможенном союзе и Едином экономическом пространстве. Союз надо наделить широким набором полномочий в сфере экономического регулирования. Это позволит проводить общую и согласованную политику в ключевых отраслях, повысить устойчивость и потенциал развития национальных экономик, обеспечит ёмкий единый рынок и приток дополнительных инвестиций. Евразийские интеграционные процессы уже приносят вполне конкретные результаты, конкретную отдачу. Несмотря на общее замедление темпов роста мировой экономики, мирового хозяйства, в 2013 году товарооборот в рамках тройки не только не снизился, а чуть-чуть всё-таки увеличился и составил 64,1 миллиарда долларов. При этом улучшается структура взаимной торговли, сокращается доля сырьевых ресурсов в экспортно-импортных операциях, причём это изменение идёт за счёт повышения технологической продукции, за счёт товаров с высокой добавленной стоимостью, – и изменения значительные. В общей структуре с 28,9 процента доля высокотехнологичной продукции увеличилась до 40 процентов. Интеграция создаёт предпосылки для равноправной конкуренции на рынке государств Таможенного союза. Расширяется потребительский спрос. Тем самым стимулируется инновационная активность наших компаний, производители более эффективно используют имеющиеся ресурсы. Приоритетным направлением интеграционного взаимодействия стал учёт интересов бизнес-сообщества. Евразийская экономическая комиссия наладила тесные сотрудничества с объединениями деловых кругов наших стран, консультируется с предпринимателями по вопросам совершенствования нормативной базы Таможенного союза и Единого экономического пространства. Я скажу больше, не просто консультируется: по сути, представители бизнес-кругов включены в этот процесс и являются соавторами всех этих документов. Евразийский интеграционный проект привлекает наших партнёров по СНГ. В наиболее продвинутой стадии находятся переговоры о подключении к нему и Армении, и Кыргызстана. С армянской стороной принят и успешно реализуется план мероприятий по адаптации к нормам и требованиям Таможенного союза и Единого экономического пространства. Поэтому считаем возможным перейти к подготовке проекта договора о присоединении Армении к будущему Евразийскому экономическому союзу. Конечно, нужно все минусы и плюсы здесь взвесить, причём для всех участников этого процесса. Важно продолжить и содействие Кыргызстану по присоединению. Необходимо вместе с нашими партнёрами утвердить дорожную карту дальнейших действий. Ключевой экономический партнёр Таможенного союза – Украина. Нас объединяют тесные промышленные и торговые связи. Украинцы входят в зону свободной торговли СНГ. Экстраординарная ситуация, сложившаяся на Украине, вызывает серьёзное беспокойство. Украинская экономика находится в тяжёлом, если не сказать тяжелейшем кризисе. Возможны негативные последствия и для рынка Таможенного союза. Поэтому нужно вместе подумать над тем, что бы предпринять в целях защиты наших производителей и экспортёров, а также проработать параметры дальнейшего взаимодействия с Украиной. Безусловно, нам нужно сделать всё, чтобы помочь нашим партнёрам выйти из той сложной ситуации, в которой они сегодня находятся. Мы, конечно, обсудим сегодня и другие аспекты, касающиеся ситуации вокруг Украины. Евразийское интеграционное объединение открыто к сотрудничеству со всеми государствами и уже приступило к формированию пакета соглашений о свободной торговле с рядом государств. Получено около 40 предложений о заключении таких договоров, в том числе от Европейской ассоциации свободной торговли: это Исландия Лихтенштейн, Норвегия, Швейцария, – от Вьетнама, Израиля, Индии, Чили, Перу. И в заключение подчеркну: Россия дорожит конструктивными, равноправными и открытыми отношениями, которые сложились в сфере экономики между нашими странами, высоко ценит достигнутые совместные результаты. Убеждён, евразийская экономическая интеграция открывает перед участниками этого проекта новые, уникальные возможности, которые могут и должны быть использованы на благо граждан наших стран. Я вас благодарю за внимание и хочу передать слово нашим сегодняшним гостям. Пожалуйста. А.ЛУКАШЕНКО: Уважаемые коллеги! Сегодня мы собрались, чтобы обсудить ход работы над проектом договора о Евразийском экономическом союзе. Учитывая, что Президент России очень подробно изложил ситуацию вокруг Единого экономического пространства, охарактеризовал направления нашей работы по формированию договора, я ограничусь только несколькими проблемами, которые надо решать. И изложу свою позицию с точки зрения Белоруссии, как мы это видим. Мы планировали собраться в середине марта. Но эксперты после работы в Астане нас подтолкнули к тому, чтобы мы решили ряд вопросов на нашем уровне, чтобы дать им возможность работать более активно. В противном случае, как они сказали, можем не успеть к середине этого года создать мощный правовой механизм нашего экономического союза. Поэтому мы перенесли немного эту встречу. Наверное, правильно сделали. Это даст возможность комиссии и специалистам пару недель уже иметь в резерве, для того чтобы подготовить договор к рассмотрению на высшем уровне. На предыдущей встрече в Москве нами определены вопросы для дополнительной проработки. Перед экспертами поставлена задача – завершить работу по их согласованию. Как меня информировали, в подготовке документов удалось продвинуться вперёд, но отдельные аспекты всё же требуют решения на нашем уровне, о чём я только что сказал. Надеюсь, что в ходе сегодняшней встречи нам удастся найти взаимоприемлемое решение, чтобы подписать договор в согласованные сроки. Мы не можем повторить тот печальный опыт, который был характерен для нас в рамках СНГ. Мы очень много говорили об СНГ. Говорили-говорили и заговорили. Люди ждали от нас шагов по формированию в рамках СНГ нормальных отношений и союза. Не получилось. И у людей очень большая настороженность, чтобы это не произошло с нашим Таможенным союзом и Единым экономическим пространством. У нас просто нет выбора и нет выхода: мы должны в заявленные сроки подготовить договор и в заявленные сроки его подписать. В противном случае нас люди не поймут. Хотел бы отметить два момента, принципиальных для Беларуси и, наверное, важных для всех наших стран. Во-первых, в нашем интеграционном проекте мы должны выйти на конкретные результаты. Таким результатом является завершение создания Таможенного союза без каких-либо ограничений и изъятий. В этом вопросе стороны продвинулись дальше всего. Фактически остались изъятия лишь по некоторым, однако весьма чувствительным товарам, включая алкоголь, табак, лекарства, нефть, газ. И нам необходимо принять по ним принципиальное решение. Однако появились подходы, когда отмену изъятий по товарам начали увязывать с отменой изъятий по услугам, капиталу, рабочей силе. Наша принципиальная позиция – создание Евразийского экономического союза должно базироваться на полномасштабном Таможенном союзе, без изъятий, в том числе без пошлин, количественных ограничений или чего-то другого. Свобода движения товаров должна стать примером для решения задач по реализации остальных трёх свобод. Без этого будущий экономический союз лишится прочного фундамента. Одновременно мы продолжаем целенаправленно работать над реализацией тех договорённостей, которые закреплены в базовых соглашениях Единого экономического пространства. Во-вторых, по проекту договора. Позиция белорусской стороны по отдельным положениям институциональной части договора была изложена в ходе нашей предыдущей встречи в Москве. Эксперты ведут работу по её согласованию. Думаю, нет необходимости возвращаться к этому вопросу и теперь. Функциональная часть договора, о которой только что говорил Президент России, совершенствуется, идёт работа. Хотя эта работа активизировалась, однако готовность проекта оценивается всё теми же экспертами примерно 70–80 процентами, о которых были проинформированы на нашей прошлой встрече. Сближения по наиболее чувствительным позициям для каждой из сторон практически не произошло, в том числе по формированию общего энергетического рынка, либерализации автомобильного транспортного рынка, доступу к газотранспортной системе, правилам субсидирования сельского хозяйства стороны постоянно выдвигают новые предложения, которые могут размыть уже имеющиеся договорённости. Поэтому предлагаю в нашей дальнейшей работе по проекту договора руководствоваться следующим подходом. Совершенствовать нормативно-правовую базу ЕЭП при согласии с предлагаемыми изменениями всех трёх сторон. Если же кто-то против, то включать в проект договора нормы соглашений ЕЭП в их неизменном состоянии, которые есть сегодня, чтобы не допустить отхода, отката назад, потому что по некоторым позициям эксперты нам говорят о том, что это уже происходит при обсуждении. В противном случае мы рискуем неоправданно затянуть процесс подготовки договора и, соответственно, начало работы Евразийского экономического союза. Вот два принципиальных момента, на наш взгляд, по которым мы должны принять решения и более активно двигаться в направлении создания нашей экономической системы, экономического союза. Будем откровенно говорить, события в мире нас очень активно подталкивают к тому, чтобы этот процесс ускорять. Нам, наверное, меньше надо посматривать по сторонам, а заниматься своими делами, своими государствами, тогда нас и уважать будут, и ценить будут. Благодарю. | I6: https://eccis.org/news/2830/suzet-5-marta-v-moskve-sostoalos-zasedanie-vyssego-evrazijskogo-ekonomiceskogo-soveta | J6: 12 | K6: 0 | L6: 13 | M6: 0 | N6: 0 | O6: 30 | P6: 2
A7: Россия | B7: 2015 | C7: 8 мая | E7: Путин | F7: заседание ВЕЭС | G7: Москва | H7: В.Путин: Уважаемые коллеги, добрый день! Наше заседание – первое с начала работы Евразийского экономического союза. Я очень рад отметить, что большинство принятых решений по запуску евразийского интеграционного проекта реализовано в полной мере и в сроки, о которых мы договаривались. На мировой арене появилось новое экономическое объединение с едиными правилами движения товаров, услуг, капитала, трудовых ресурсов. Со 2 января полноправным членом союза стала Армения, и уже приняты решения – надеюсь, после ратификации всё это вступит в силу – по присоединению Киргизии в полномасштабном формате. Важно, что у всех участников Евразийского союза есть настрой на углубление интеграции. Более тесные торговые инвестиционные связи несомненно будут способствовать дальнейшему социально-экономическому развитию наших стран, будут укреплять конкурентоспособность нашего объединения в мировой экономике и в конечном счёте обеспечат рост благосостояния населения наших стран. Евразийская интеграция доказывает свою эффективность: взаимный товарооборот стран-участниц вырос почти на двадцать миллиардов долларов, улучшилась инфраструктура торговли, возросла доля товаров с высокой добавленной стоимостью и сократилась доля сырья, причём сократилась значительно – с 40 до 28,9 процента. На 2015–2016 годы в рамках Евразийского союза согласованы общие макроэкономические ориентиры роста, запланирован комплекс мер по стимулированию хозяйственного развития, углублению сотрудничества в реальном секторе и улучшению делового климата. Предлагаем подумать над возможностью более тесного взаимодействия в сфере монетарной политики. Убеждён, действуя слаженно, центробанки наших стран могли бы эффективнее противостоять негативному влиянию резких колебаний курсов валют. Мы прекрасно отдаём себе отчёт в том, что это дело будущего. Здесь никто не собирается забегать вперёд. Согласованные действия монетарной политики должны быть основаны на интеграционных процессах в экономической прежде всего сфере после достижения определённого уровня взаимодействия. Обсуждать эти вопросы, говорить, думать об этом – всё это можно делать уже сейчас. В завершающей стадии находится работа по созданию общего рынка энергоресурсов Евразийского союза. На наше утверждение представлена концепция единого рынка электроэнергетики, который начнёт функционировать с 2019 года. Этот документ определяет этапы формирования, механизмы регулирования, порядок взаимной торговли электроэнергией. Продолжается формирование общего транспортного пространства Евразийского союза. Нам предстоит утвердить программу поэтапной либерализации рынка автомобильных грузоперевозок. Ставится задача сократить транспортные издержки, развить добросовестную конкуренцию в данном секторе услуг. Будет обеспечена гармонизация правил и требований для автоперевозчиков. По линии национальных корпораций развития разрабатываются совместные программы кредитования экспортёров на внешних рынках. Это поможет выправить недавний спад в нашей торговле с третьими странами. Идёт создание евразийской системы «единого окна» для бизнеса. Её запуск позволит унифицировать фискальные, таможенные и административные процедуры внешнеэкономической деятельности. До конца года нам предстоит серьёзно обновить договорно-правовую базу: в работе находятся более 50 проектов документов. Нужно, в частности, принять новый Таможенный кодекс, подписать соглашение о взаимодействии в валютно-финансовой и социально-экономической сферах. Завершить работу по большинству документов необходимо к следующему заседанию совета – это октябрь, в Астане. Интерес к углублению отношений с союзом проявляют и зарубежные партнёры. Налажено взаимодействие со структурами ООН. В сентябре на 70-й сессии Генеральной Ассамблеи ООН Евразийский экономический союз должен получить статус наблюдателя. Важно, чтобы наши внешнеполитические ведомства координировали усилия при рассмотрении в ООН соответствующей заявки. Евразийская экономическая комиссия ведёт переговоры по соглашениям по свободной торговле с рядом государств. Согласован и будет подписан в ближайшее время договор с Вьетнамом, аналогичные документы прорабатываются на экспертном уровне с Израилем, Индией, Египтом. Перспективным представляется развитие экономического сотрудничества Евразийского союза с Китайской Народной Республикой, говорил об этом сегодня и на встрече с Председателем КНР Си Цзиньпином. Кстати говоря, Председатель КНР также проявляет к этому интерес и говорит о том, что этот процесс вполне можно было бы вписать в «Экономический пояс так называемого Шёлкового пути» – проект, который продвигается нашими друзьями в Китае. Считаю целесообразным поручить Евразийской комиссии начать переговоры с КНР о заключении соглашения с КНР о торгово-экономическом сотрудничестве. На перспективу, думаю, стоит подумать над возможностью гармоничного совмещения Евразийской экономической интеграции и, как я уже сказал, китайской инициативы «Экономического пояса Шёлкового пути». Убеждён, тесная кооперация с китайскими партнёрами будет способствовать притоку инвестиций в государства союза, поможет создать новые рабочие места, эффективнее освоить евразийский транспортный потенциал. Я хочу вас поблагодарить за внимание и передаю слова Александру Григорьевичу Лукашенко, Президенту Беларуси, которая председательствует в этом году в Евразийском экономическом союзе. | I7: http://www.kremlin.ru/catalog/persons/119/events/49435 | J7: 15 | K7: 0 | L7: 6 | M7: 0 | N7: 0 | O7: 10 | P7: 0
A8: Россия | B8: 2015 | C8: 16 октября | E8: Путин | F8: заседание ВЕЭС | G8: Астана | I8: нет полного текста речи | J8: - | L8: - | M8: - | N8: - | O8: - | P8: -
A9: Россия | B9: 2015 | C9: 21 декабря | E9: Путин | F9: заседание ВЕЭС | G9: Москва | I9: нет полного текста речи | J9: - | L9: - | M9: - | N9: - | O9: - | P9: -
A10: Россия | B10: 2016 | C10: 26 декабря | D10: в узком составе | E10: Путин | F10: заседание ВЕЭС | G10: Санкт-Петербург | H10: В.Путин: Уважаемые коллеги! Я на правах хозяина несколько слов скажу, а потом передам слово Нурсултану Абишевичу, который возглавляет Высший Евразийский экономический совет, Казахстан у нас в этом году его возглавляет. Но прежде чем мы начнём работать, хочу вас всех поприветствовать в Петербурге. Евразийскому экономическому союзу исполняется два года, поэтому у нас есть хороший повод подвести итоги совместной работы за этот период и обменяться мнениями о перспективах дальнейшего развития евразийской интеграции. В процессе строительства Евразийского экономического союза мы вместе добились действительно серьёзных успехов. Создан ёмкий общий рынок, действующий по согласованным правилам, основанным на универсальных принципах Всемирной торговой организации, заметно повысились показатели и взаимной торговли. Последовательно устраняются барьеры на пути свободного движения товаров, услуг, рабочей силы и капитала. За время функционирования союза число нетарифных ограничений сокращено более чем на 30 процентов. В этом году заработал единый рынок лекарственных средств и медицинских изделий. Это поможет снизить цены на социально важную фармацевтическую продукцию, а также позволит усилить контроль за её качеством и порядком обращения. Эффективнее станет и борьба с контрафактом. В рамках Союза приняты Концепции формирования к 2025 году общих рынков газа, нефти и нефтепродуктов. Разрабатываются универсальные правила торговли электроэнергией и доступа к услугам субъектов естественных монополий в этой области. Ведётся совершенствование союзных правил регулирования в антимонопольной сфере. Продолжается работа над созданием к 2025 году общего финансового рынка. Согласованный экспертами проект Концепции поэтапной либерализации этого сектора экономики предусматривает гармонизацию действующих в наших странах правил осуществления кредитно-денежных, валютных, банковских, страховых операций. Последовательно совершенствуется и договорно-правовая база Евразийского экономического союза. Мы многое сделали по подготовке нового Таможенного кодекса. В Кодекс заложен целый ряд важных правовых нововведений, отвечающих самой передовой мировой практике. Заметно возрастают полномочия Евразийской комиссии по вопросам таможенного регулирования, предусматривается широкое использование цифровых технологий при проведении процедур оформления товаров на внешних границах Союза. Одним из ключевых приоритетов деятельности Евразийского экономического союза становится формирование благоприятной деловой среды для полноценного раскрытия имеющегося у наших стран производственного и технологического потенциала. Необходимо активнее содействовать предприятиям наших стран в развитии промышленной кооперации, энергичнее вовлекать в производственные и технологические цепочки малый и средний бизнес. Первоочередной задачей на ближайшую перспективу видится формирование единого цифрового пространства Евразийского экономического союза. Недавно подробно мы у себя, в Москве, обсуждали с Председателем Коллегии Евразийской комиссии Тиграном Суреновичем Саркисяном эту тему. И я с ним полностью согласен, в последние годы цифровая экономика получила широкое распространение, прежде всего в таких странах, как Китай, Соединённые Штаты, и отставание государств Евразийского союза в области глобальной электронной торговли и межотраслевых цифровых платформ может сказаться на нашей конкурентоспособности как на внешних, так и на внутренних рынках самого Союза. Я в детали здесь вдаваться не буду. Хочу отметить только, что у нас развивается и на внешнем контуре интересная и плодотворная работа с нашими возможными партнёрами. С Вьетнамом, как вы знаете, уже достигнуто Соглашение о свободной торговле. Интересуются таким же развитием отношений с нами Израиль, Индия, Иран, Сингапур, Египет. У нас ведётся работа и с Китайской Народной Республикой. Но всё это мы вместе с вами сможем сегодня обсудить. Я хочу вас всех ещё раз сердечно поприветствовать в Петербурге. Спасибо большое. <…> | I10: http://www.kremlin.ru/events/president/news/53596 | J10: 10 | K10: 0 | L10: 8 | M10: 0 | N10: 0 | O10: 7 | P10: 0
A11: Россия | B11: 2016 | C11: 31 мая | D11: в расширенном составе | E11: Путин | F11: заседание ВЕЭС | G11: Астана | H11: В.Путин: Уважаемые коллеги! За полтора года работы Евразийского экономического союза нам действительно многое удалось сделать в продвижении этого масштабного интеграционного проекта, главное – с полным основанием можно констатировать, что союз состоялся как современная международная организация, нацеленная на решение конкретных задач экономического развития наших стран. После присоединения Армении и Киргизии евразийской «пятёркой» сформирован ёмкий общий рынок с населением более 182 миллионов человек, обеспечена преемственность в управлении интеграционными процессами со стороны наднационального органа союза – Евразийской экономической комиссии. С 1 февраля назначен новый состав её Коллегии, который без раскачки включился в работу. В соответствии с решаемыми задачами усовершенствована и структура самой Комиссии. Создана солидная договорно-правовая база, которая расширяется на основе согласованных нами планов. В развитие учредительного Договора о Евразийском экономическом союзе принято более 60 соглашений. По ряду направлений работу необходимо продолжать и далее в таком же активном темпе. Это касается, в частности, подготовки нового Таможенного кодекса и Соглашения о порядке заключения союзом международных договоров, то есть дальнейшее продвижение интеграции зависит от своевременного принятия необходимых для нашего развития нормативных документов. Многого удалось достичь в деле сокращения взаимных барьеров на пути свободного движения товаров, рабочей силы, услуг и капитала. Не могу не согласиться с коллегами, которые выступали по поводу того, что их ещё очень много. Напомню только, что из выявленных на этапе подготовки Договора о союзе 422 торговых ограничений более 80 уже устранено, ещё около 30 находятся в процессе отмены, а 16 должны быть ликвидированы в течение текущего, 2016 года. Крайне важно продолжить унификацию нетарифного регулирования, развивать механизмы отслеживания движения товаров от момента их ввоза на таможенную территорию союза до их передачи потребителю, совершенствовать взаимодействие в сфере санитарно-эпидемиологического контроля. Необходимо и далее уделять приоритетное внимание проведению согласованной политики в ключевых секторах экономики, а также гармонизации законодательства в области естественных монополий. Перспективным видится подключение государств союза к программе импортозамещения, проводимой в России. Мы приглашаем всех наших партнёров к совместному производству оборудования и комплектующих более чем в 25 отраслях, включая машиностроение, электронную и лёгкую промышленность, сельское хозяйство. К 2019 году должен быть сформирован общий рынок электроэнергии, утверждена его концепция, начата подготовка соответствующей программы. По оценкам экспертов, реализация этой задачи обеспечит дополнительный прирост ВВП государств – членов союза в размере 7 миллиардов долларов. Сегодня мы сделаем очередной шаг к созданию к 2025 году единого рынка углеводородов, о чём мы с вами очень много говорили и спорили в своё время, примем соответствующие документы, которые предусматривают равные условия конкуренции на территории всего союза, что даст совокупный эффект в газовой отрасли более 1 миллиарда долларов, а в нефтяной – до 8 миллиардов в год. Уже в текущем году заработает общий рынок в социально значимой сфере лекарственных средств и медицинских изделий. На завершающем этапе находится согласование договорённостей о правилах и принципах обращения этой продукции. Поступательно развивается наше сотрудничество в инновационной сфере. Создаётся Евразийский инжиниринговый центр по станкостроению, совместно разрабатываются евразийские технологические платформы. Неотъемлемой составляющей интеграционного процесса является либерализация торговли услугами. В текущем году предстоит принять дорожные карты по унификации законодательства в области строительства и проектирования, проведения научных исследований, а также в туризме. Единые правила уже охватывают 43 сервисных сектора, или более 50 процентов от общего объёма производимых в Союзе услуг. Весьма перспективной представляется идея создания единого информационного пространства. Предложили бы Комиссии подготовить соображения на этот счёт. Эффективному функционированию интеграционного объединения способствует системное выстраивание отношений с внешними партнёрами. Мы поддерживаем предложение казахстанского председательства сконцентрировать усилия на дальнейшем углублении экономических связей Союза с другими странами и интеграционными объединениями, в первую очередь с государствами Шанхайской организации сотрудничества и АСЕАН. На этом направлении уже сделано немало. Создана зона свободной торговли с Вьетнамом, готовится перечень конкретных проектов в развитие идеи сопряжения Евразийского экономического союза с китайской инициативой «Шёлкового пути». Евразийской комиссией подписаны меморандумы о взаимопонимании с правительствами Монголии, Перу, Чили. В планах – разработка торговых договорённостей с Сербией. Готовятся соглашения о сотрудничестве с Южной Кореей, Эквадором и МЕРКОСУР. Интерес к установлению тесных связей с союзом проявляют Иран, Индия, Египет, Израиль. Приветствуем также инициативу казахстанских партнёров о проведении международной конференции по налаживанию взаимодействия между Евразийским союзом и ЕС. Необходимо, чтобы Евразийская экономическая комиссия активно подключилась к её проработке. И ещё хотел бы отметить большую практическую поддержку, которую оказывает созданный год назад Евразийский деловой совет. Считаю это направление тоже чрезвычайно важным. Недавно его возглавил Виктор Борисович Христенко, имеющий хороший опыт работы в наших интеграционных структурах. И в заключение, пользуясь возможностью, хотел бы пригласить всех вас, как мы в узком составе договорились, провести нашу следующую встречу в декабре, по традиции, в Москве. Спасибо за внимание. | I11: http://www.kremlin.ru/catalog/persons/119/events/52049 | J11: 11 | K11: 0 | L11: 11 | M11: 0 | N11: 0 | O11: 19 | P11: 1
A12: Россия | B12: 2017 | C12: 14 апреля | E12: Путин | G12: Бишкек | H12: В.Путин: Уважаемые коллеги! Уважаемый Председатель! Прежде всего хочу, так же как и присутствующие здесь главы государств, искренне поприветствовать Президента Молдавии Игоря Николаевича Додона, который впервые участвует в заседании Высшего Евразийского экономического совета. На заседании Высшего Евразийского экономического совета. На заседании Высшего Евразийского экономического совета. Отмечу, что сотрудничество в рамках ЕАЭС продвигается успешно. Мы вместе добились результатов в деле формирования и укрепления ёмкого общего рынка с универсальными правилами для экономических операторов. Можно с полной уверенностью сказать, что наш общий рынок сработал в качестве своеобразной подушки безопасности, несмотря на определённые издержки, связанные с внешней конъюнктурой, которая сложилась неблагоприятно (об этом уже было здесь сказано). Тем не менее как подушка безопасности наши интеграционные институты сработали, в определённой степени нивелировали воздействие неблагоприятной внешней конъюнктуры, а национальные экономики смогли адаптироваться к новым реалиям. Это действительно так. Обращаю внимание, что в январе текущего года по сравнению с январём прошлого года объём взаимной торговли в рамках союза вырос на 38 процентов. Как Нурсултан Абишевич говорил, кризисы приходят, но они рано или поздно заканчиваются. 38 процентов у нас плюс, а поставки государств-членов в третьи страны выросли на 37 процентов. Существенно улучшилась (и это отмечаю как, наверное, самое главное) структура экспортно-импортных операций, снизился удельный вес сырья в торговле в 2016 году и обозначился рост доли машин, транспортных средств и оборудования, продовольственных и сельхозтоваров. В рамках ЕАЭС мы вместе добились результатов в деле формирования и укрепления ёмкого общего рынка с универсальными правилами для экономических операторов. В 2016 году производство в сфере сельского хозяйства союза увеличилось почти на четыре процента. Наметился рост в промышленности. Рассчитываем на позитивную динамику в этих отраслях и в текущем году. Отдельно хотел бы отметить, что существенная часть этого прироста приходится именно на российский рынок, который всё более активно осваивается государствами – членами ЕАЭС. Это выгодно как нашим партнёрам по союзу, так и российским потребителям. В 2016 году на Россию пришлось около 62 процентов объёма совокупных внутрисоюзных поставок. Во многом благодаря рынку союза в Казахстане развивается новая отрасль – автомобилестроение. Хочу проинформировать Нурсултана Абишевича: мы приняли решение по Вашему предложению о продолжении расширения нашего сотрудничества в космосе с использованием Байконура. Мы все наши планы скорректируем в самое ближайшее время, имею в виду использование космодрома Восточный, с тем, чтобы активно вместе с вами работать по имеющимся у нас проектам, которые вы сформулировали. С использованием не только Байконура на длительную перспективу, но и с реализацией тех планов по совместным пускам, по разработке новых видов ракетно-космической техники. Шагом к укреплению ЕАЭС является сопряжение информационных систем наших госорганов, прежде всего таможенных служб, с целью создания механизма мониторинга движения товаров по территории союза. В Киргизии создаются условия для восстановления текстильного и швейного производства. Как известно, в 2016 году экспорт киргизских товаров лёгкой промышленности в страны союза вырос на 38 процентов. Товарооборот сельхозпродукции между Арменией, скажем, и Россией также увеличился, причём на солидную величину – в 22 процента. Развивается кооперация с Республикой Беларусь, причём развивается очень активно. По некоторым крупным предприятиям взаимная зависимость составляет сейчас 40 и более процентов. Многие виды товаров, произведённые в Белоруссии, рассматриваются в Российской Федерации как производство отечественного производителя и пользуются такими же льготами при государственных закупках на территории Российской Федерации. В последнее время проделана значительная работа по совершенствованию договорно-правовой базы союза: согласованы такие фундаментальные документы, как Таможенный кодекс, Концепция формирования общих рынков газа, нефти и нефтепродуктов, поэтапной либерализации финансового рынка. По всем этим направлениям удалось выйти на взаимоприемлемые решения. Приоритетное внимание необходимо уделять дальнейшей работе по улучшению макроэкономической ситуации, увеличению объёмов инвестиций в основной капитал, созданию большей добавленной стоимости и развитию несырьевого экспорта. Российский рынок всё более активно осваивается государствами – членами ЕАЭС. Это выгодно как нашим партнёрам по союзу, так и российским потребителям. Важную роль в решении актуальных вопросов экономического роста, обеспечения финансовой стабильности наших стан играет Евразийский банк развития и управляемый им Евразийский фонд стабилизации и развития. Банк выполняет значимую роль в осуществлении крупных инвестиционных инициатив. На реализацию этих целей уже предусмотрено около четырёх миллиардов долларов. Последний пример такого сотрудничества – недавно подписанное соглашение о предоставлении Киргизской Республике кредита на сумму 110 миллионов долларов для финансирования конкретных инфраструктурных проектов в республике. Одной из насущных задач является последовательное устранение препятствий на пути свободного движения товаров, рабочей силы, услуг и капиталов. Такие барьеры у нас ещё, к сожалению, сохраняются, но мы договорились о том, что постепенно будем их устранять. В соответствии с Договором о союзе эти процессы будут планомерно реализовываться до 2025 года. Ещё одним шагом к укреплению ЕАЭС является сопряжение информационных систем наших госорганов, прежде всего таможенных служб, с целью создания механизма мониторинга движения товаров по территории союза. Это позволило бы либерализовать и улучшить решение таких проблемных вопросов для транзита товаров третьих стран, в том числе и Украины. Мы об этом с вами дискутировали неоднократно и пришли к выводу, что введение этой электронной системы отслеживания движения товаров помогло бы и нашим партнёрам, которые находятся вне союза. Проделана значительная работа по совершенствованию договорно-правовой базы союза: согласованы такие фундаментальные документы, как Таможенный кодекс, Концепция формирования общих рынков газа, нефти и нефтепродуктов, поэтапной либерализации финансового рынка. Эффективный контроль невозможен без внедрения обязательного оформления товаросопроводительных документов в электронной форме. Это передовая мировая практика. С учётом технических особенностей подобных проектов необходимо в максимально короткий срок завершить подготовку соответствующего соглашения. Если говорить о международной деятельности союза, напомню, что уже действует соглашение о свободной торговле с Вьетнамом, ведутся переговоры с Китайской Народной Республикой, Израилем, Сербией, Египтом, Индией, Сингапуром, и уже упоминалось здесь о наших контактах и соответствующей работе с Ираном. Мы также контактируем активно с Шанхайской организацией сотрудничества, АСЕАН и другими организациями. Развитие внешнего контура нашего интеграционного объединения должно быть продолжено на системной и плановой основе. В заключение хотел бы сказать и выразить надежду, что Евразийский союз продолжит крепнуть и расти на благо народов наших стран. Думаю, что у нас есть все основания для такого оптимизма. Спасибо большое за внимание. | I12: http://www.kremlin.ru/events/president/transcripts/54293 | J12: 6 | K12: 1 | L12: 14 | M12: 0 | N12: 0 | O12: 21 | P12: 0
A13: Россия | B13: 2017 | C13: 11 октября | D13: в расширенном составе | E13: Путин | F13: заседание ВЕЭС | G13: Сочи | H13: В.Путин: Уважаемые коллеги! Рад вас всех ещё раз поприветствовать на нашей встрече, и в том числе нашего гостя – Президента Молдавии Игоря Николаевича Додона. Только что в узком составе мы обсудили текущие вопросы деятельности Евразийского экономического союза, подвели некоторые итоги интеграционной работы и приняли ряд важных решений. Можно с уверенностью сказать, что союз успешно функционирует и развивается. Интеграция положительно сказывается на темпах экономического роста наших государств. Совокупный ВВП Евразийского экономического союза увеличился в текущем году на 1,8 процента. Позитивная динамика фиксируется в стратегических производственных отраслях: в промышленности рост составил 2,4 процента, в сельском хозяйстве – почти 1 процент, расширились грузовые, пассажирские перевозки соответственно на 6,9 и на 7,8 процента. Возросли объёмы внешней торговли союза – плюс 26 процентов, а положительное сальдо экспортно-импортных операций превысило 77 миллиардов долларов. При этом доля машин, оборудования и транспортных средств достигла 17,5 процента. Удельный же вес энергетических товаров снизился до 28 процентов. Товарооборот между государствами – членами Евразийского экономического союза увеличился в текущем году на 30 процентов. Товарооборот между государствами – членами Евразийского экономического союза увеличился в текущем году на 30 процентов. Это прямое следствие того, что мы создали в рамках союза единый рынок и общее экономическое пространство. Убеждены, нужно продолжать системную работу по устранению ограничений, мешающих свободному передвижению товаров, рабочей силы, услуг и капитала между нашими государствами. Следует ускорить разработку дорожной карты по ликвидации имеющихся пока ещё барьеров в сфере промышленности, агропромышленном комплексе, энергетике, техническом регулировании. Государствам – членам Союза предстоит завершить все внутренние процедуры, чтобы, как запланировано, с 1 января будущего года вступил в силу новый Таможенный кодекс Евразийского экономического союза. В свою очередь, Евразийская экономическая комиссия должна заранее принять технические решения, необходимые для практического применения кодекса во внутрисоюзной торговле. Государствам – членам Союза предстоит завершить все внутренние процедуры, чтобы с 1 января будущего года вступил в силу новый Таможенный кодекс ЕАЭС. В ходе заседания в узком составе мы также утвердили новый важный документ, который называется «Основные направления цифровой повестки Союза до 2025 года». Напомню, инициатива его разработки была выдвинута на заседании нашего Союза ещё в декабре прошлого года. Россия готова активно участвовать в практической реализации цифровой повестки. Речь идёт о проведении согласованной со странами Союза политики в области развития интернет-экономики, формирования общих правил цифровой торговли, единых стандартов обмена информацией и её защиты. Отмечу, принимаемые нами сегодня решения о налаживании сотрудничества в области космических и геоинформационных услуг, а также об объединении действующих в государствах Евразийского экономического союза национальных систем дистанционного зондирования Земли также являются одним из очень важных наших решений. В числе ключевых задач видим совершенствование кредитно-финансовой инфраструктуры Евразийского экономического союза. Предлагаем эффективнее задействовать потенциал Евразийского банка развития и Евразийского фонда стабилизации для обеспечения роста экономик наших стран, использовать специальные инвестиционные механизмы Евразийского банка и Стабфонда для укрепления финансовой устойчивости государств – членов Союза. В числе ключевых задач видим совершенствование кредитно-финансовой инфраструктуры ЕАЭС. Предлагаем эффективнее задействовать потенциал Евразийского банка развития и Евразийского фонда стабилизации. Особого внимания, как представляется, требуют вопросы, связанные с продвижением позиций Евразийского экономического союза на международной арене, развитием связи нашего объединения с другими государствами. В этом контексте считаем важным налаживать более тесную кооперацию с партнёрами из СНГ, которые не входят в Евразийский экономический союз. Мы сегодня достаточно подробно говорили об этом и о том, что нам нужно утвердить статус наблюдателя. Стоит ускорить и уже начатый переговорный процесс о создании зон свободной торговли с теми странами, с которыми договорились выстраивать такую работу и с которыми Комиссия уже ведёт работу. Большое значение придаём подготовке проекта соглашений о сотрудничестве между Евразийским экономическим союзом и этими странами. В заключение хотел бы высказать признательность киргизским друзьям за большую работу, проделанную в ходе председательства Киргизии в органах Евразийского экономического союза в текущем году. В качестве следующего председателя Россия готова к интенсивному взаимодействию со всеми партнёрами по союзу в целях дальнейшего укрепления нашего интеграционного объединения. Позвольте передать слово Президенту Армении Сержу Азатовичу Саргсяну. В.Путин: Уважаемые коллеги! Хочу всех вас поблагодарить за сегодняшнюю достаточно конструктивную, содержательную работу. В узком составе мы дискутировали практически по всем вопросам, глубоко погружались во все проблемы. Надеюсь, что такая же содержательная работа сохранится в будущем. Хочу пожелать Комиссии, всем нашим коллегам, которые занимаются работой в рамках нашего объединения, в рамках нашего союза, так же интенсивно работать в будущем. Россия берёт на себя обязанности председателя в следующем году. Заверяю вас, что мы будем делать всё, что от нас зависит, чтобы наше объединение развивалось, и развивалось успешно. Нурсултан Абишевич сегодня предложил созвать и внеочередной саммит, посвящённый развитию цифровых технологий, цифровой экономики. Мы все это поддержали. Согласуем с Казахстаном время, место, с удовольствием примем участие. | I13: http://www.kremlin.ru/events/president/news/55819 | J13: 17 | K13: 0 | L13: 9 | M13: 0 | N13: 0 | O13: 6 | P13: 0
A14: Россия | B14: 2018 | C14: 14 мая | D14: в расширенном составе | E14: Путин | F14: заседание ВЕЭС | G14: Сочи | H14: В.Путин: Уважаемые коллеги! Только что мы завершили заседание Высшего Евразийского экономического совета в узком составе. Обсуждены важные аспекты деятельности Евразийского союза и достигнут ряд договорённостей. Не скрою, это не без дискуссий, не без споров, но нам удалось всё-таки добиться общих решений. Отмечу решение об учреждении статуса страны-наблюдателя при ЕАЭС, согласован вопрос, чтобы такой статус был предоставлен Республике Молдова. В этой связи хотел бы поприветствовать присоединившегося к нашему заседанию Президента Игоря Николаевича Додона. Рассчитываем, что Республика Молдова в качестве наблюдателя будет активно участвовать в деятельности нашего интеграционного объединения. Мы готовы рассмотреть заявки и других заинтересованных стран, прежде всего наших соседей – государств СНГ. В ходе заседания в узком составе подробно обсуждены и другие актуальные вопросы взаимодействия «пятёрки». Россия как председатель ЕАЭС высказала свои соображения по повестке интеграционной работы на 2018 год. В числе первоочередных задач – повышение эффективности функционирования общего внутрисоюзного рынка, сближение национальных правил экономического регулирования. Приоритетное внимание по-прежнему будет уделяться устранению остающихся ограничений и изъятий на пути свободного перемещения товаров, капиталов, рабочей силы. Ориентируемся на создание наиболее комфортных условий для развития предпринимательской активности, в том числе за счёт системной работы с деловыми кругами и учёта их пожеланий. Хорошие возможности для наращивания сотрудничества открываются в атомной энергетике, в области возобновляемых энергоисточников, в экологии, медицине, космосе. В этих передовых отраслях важно расширять производственную кооперацию, совместно работать над новыми технологиями и ноу-хау, внедрять инновации, отвечающие требованиям мировой экономики, глобального технологического развития. Ещё один приоритет – реализация цифровой повестки ЕАЭС. Российское председательство предлагает осуществить несколько перспективных цифровых проектов в области интернет-торговли, технологии отслеживания движения товаров, создания транспортных коридоров, промышленной кооперации. Совсем недавно по инициативе Президента Казахстана прошёл соответствующий форум по этой проблематике. Мы это всячески поддерживаем и будем работать вместе. Естественно, будут заинтересованы, рассмотрены и соответствующие инициативы наших партнёров по объединению. Об одной из них я только что сказал. Конечно, следует предпринимать дополнительные шаги по формированию единого рынка услуг ЕАЭС. В прошлом году в число секторов, функционирующих по наднациональным правилам, вошли туризм, научно-исследовательская деятельность, реклама. К концу текущего года 60 процентов общего объёма услуг будет регулироваться на основе союзного права. Хотел бы отметить, что в целом Евразийский экономический союз развивается весьма динамично. Так, например, в 2017 году валовой внутренний продукт стран-участниц вырос на 1,8 процента, промышленное производство увеличилось на 1,7 процента, а сельскохозяйственное – на 2,5 процента. Снизился уровень инфляции во всех наших государствах в среднем по Союзу до 3,1 процента. Улучшилось состояние внешней и внутренней торговли. Поставки товаров и услуг на рынки третьих стран возросли на 24,4 процента, а товарооборот между государствами – членами ЕАЭС вырос на 26 с лишним процентов. Совершенствуется сфера технического регулирования. В этих условиях по предложению Евразийской экономической комиссии создаются профильные советы руководителей ведомств, стандартизации и аккредитации. Аналогичный орган будет учреждён и для координации политики в транспортной сфере. В его задачу войдёт разработка мер по развитию рынка перевозок в рамках ЕАЭС. Также сформируем совет министров сельского хозяйства стран Союза, который займётся согласованием общей стратегии в агропромышленной сфере и продвижением союзной продукции на зарубежные рынки. Эффективно заработал Суд Евразийского экономического союза, обеспечивающий объективное юридическое рассмотрение возникающих между странами спорных ситуаций. Стоит отметить и то, что наше объединение воспринимается международными экспертами как открытый, общий рынок и единое инвестиционное и деловое пространство. В рейтинге Doing Business – 2018 ЕАЭС занимает 35-е место из 190 мест, в 2017 году это было 40-е. По отдельным индексам мы вошли в число лидеров, например регистрация собственности, присоединение к электросетям, исполнение контрактов и так далее. Развивается сотрудничество с другими странами и интеграционными объединениями. Сегодня мы подпишем соглашение о международных договорах ЕАЭС. Оно определит протокольные, юридические и организационные процедуры взаимодействия с зарубежными партнёрами. Упомяну, что успешно реализуется соглашение о зоне свободной торговли с Вьетнамом. В 2017 году совокупный экспорт государств ЕАЭС в эту страну вырос сразу на 40 процентов. На этой неделе в Астане планируется подписать соглашение о торгово-экономическом сотрудничестве с Китаем и временное соглашение об образовании зоны свободной торговли с Ираном. Продолжаются переговоры по заключению преференциальных договорённостей с Израилем, Сербией, Сингапуром. В скором времени стартуют аналогичные переговоры с Египтом и Индией. Спасибо большое за внимание, уважаемые коллеги. Передаю слово Премьер-министру Армении Николу Воваевичу Пашиняну. Пожалуйста. | I14: http://www.kremlin.ru/events/president/transcripts/57468 | J14: 5 | K14: 0 | L14: 7 | M14: 0 | N14: 0 | O14: 14 | P14: 0
A15: Россия | B15: 2018 | C15: 6 декабря | E15: Путин | F15: заседание ВЕЭС | G15: Санкт-Петербург | H15: В.Путин: Уважаемые коллеги! Друзья! Добрый день! Всех вас рад приветствовать в Петербурге. Сегодня на заседании Высшего Евразийского экономического совета предстоит подвести итоги совместной деятельности по развитию экономической интеграции в текущем году и, конечно, поговорить о планах на будущее. Подчеркну, что сотрудничество в рамках Евразийского экономического союза продвигается довольно успешно и весьма динамично, способствует более полному раскрытию экономического потенциала наших государств. Совокупный ВВП стран союза увеличился в первом полугодии 2018 года на два процента. Продолжился рост производства в промышленности: в целом по Евразэс [Евразийский экономический союз]– плюс 3,3 процента, в сельском хозяйстве – плюс 2,4 процента. На 12 процентов выросли объёмы внутрисоюзной торговли, достигнув 44 миллиардов долларов. Товарооборот с внешними партнёрами увеличился на 21 процент – до 548 миллиардов долларов, причём преимущественно за счёт наращивания нашего экспорта. Евразэс улучшил свои позиции в международных рейтингах, в частности, в ведении бизнеса: по данным Doing Business – 2018, по средневзвешенным показателям государств-членов он переместился на 31-е место. Напомню, в 2017 году это было 40-е из 190 экономик мира. В течение года российское председательство Евразэс продолжило работу по всей интеграционной повестке дня, в том числе по вопросам функционирования общего внутреннего рынка. Вместе с партнёрами по союзу сосредоточили усилия на расширении практики наднационального регулирования. На нашей встрече в мае в Сочи подписано соглашение о маркировке товаров, реализация которого обеспечит прозрачность торговых операций, позволит лучше защитить права потребителей и гарантировать равные условия конкуренции. К сегодняшнему заседанию подготовлены проекты важных решений: о создании общих рынков нефти, нефтепродуктов, газа. По оценкам экспертов, осуществление этих планов даст прибавку к ВВП наших стран до девяти миллиардов долларов. Продолжается совершенствование системы технического регулирования и контроля за качеством продукции. Единые технические стандарты уже разработаны для 85 процентов товаров, производимых нашими странами. Интенсивно развивается производственная кооперация в металлургии, электронике, химической, лёгкой промышленности и других отраслях. При этом приоритетное внимание уделяется экспортно ориентированным секторам и производству товаров с высокой долей инноваций. Сформирована нормативная и институциональная база для запуска единого цифрового пространства Евразэс. В бюджете союза на 2019 год, который нам сегодня предстоит утвердить, предусмотрены значительные средства на реализацию крупных цифровых проектов. Перспективным представляется сотрудничество государств Евразэс в сфере предоставления космических услуг, в том числе создание общей группировки орбитальных аппаратов и продвижение геоинформационных сервисов для рынков третьих стран. Можно подумать и над принятием совместной программы научно-технологического развития. Важно, что между государствами – членами Евразэс укрепляется координация в проведении валютно-финансовой и денежно-кредитной политики. В сентябре представители центральных банков подписали соглашение о гармонизации законодательства в сфере финансового рынка. Это большой шаг на пути к формированию общего финансового пространства. Предлагаем проработать вопрос о создании в Евразэс общей расчётной структуры с использованием современных финансовых технологий. Это позволило бы повысить устойчивость национальных платёжных систем наших стран, сделав их менее зависимыми от доллара и других иностранных валют. Это в прямом смысле слова повышение экономического суверенитета. Российская сторона предлагает также включить в интеграционную повестку вопросы упрощения порядка передвижения граждан, наладить более тесное взаимодействие в области здравоохранения, образования, туризма, спорта и культуры. И конечно, больше внимания следует уделять межрегиональному сотрудничеству. Продолжают расширяться и внешние связи Евразэс. В мае подписано соглашение о международных договорах с третьими странами и международными организациями. Россия выполнила необходимые для его вступления в силу внутренние процедуры. Исходим из того, что и в остальных государствах-членах этот процесс завершится в самое ближайшее время. В ноябре Евразийская экономическая комиссия заключила меморандумы о взаимодействии с исполнительным комитетом СНГ и АСЕАН. Видим в этом шаг на пути к реализации проекта большого евразийского партнёрства. Сегодня нам предстоит принять решение о вступлении в силу соглашения о торгово-экономическом сотрудничестве с Китаем и временной зоне свободной торговли с Ираном. Рассчитываем на скорейшее завершение переговоров по преференциальным торговым договорам с Сингапуром, Израилем, Сербией и – в перспективе – с Индией и Египтом. Отмечу, что по инициативе России к нынешнему заседанию подготовлен проект декларации об углублении интеграционных процессов. Речь идёт о том, чтобы не только подтвердить настрой на всемерное развитие и укрепление Евразийского союза, но и продемонстрировать, что главную стратегическую задачу интеграции мы видим в обеспечении устойчивого экономического роста государств – членов ЕврАзЭС, повышения благосостояния и улучшения качества жизни наших граждан. В следующем году на председательство в Евразэс заступает Армения. Хотел бы пожелать нашим армянским друзьям успехов. Позвольте передать слово Николу Владимировичу Пашиняну. В.Путин: Спасибо большое, уважаемый Александр Григорьевич. Думаю, что, когда пресса покинет этот зал, мы подискутируем, у нас это всегда в открытом режиме всё делается, откровенно и по-честному. Но не могу не сделать одну реплику по поводу тарифов на газ. У нас выработан план движения к 2025 году, когда мы должны согласовать единые рынки нефти, газа, нефтепродуктов. Что касается сегодняшней ситуации, то она заключается в том, что важен не тариф, а важна конечная цена газа, в которую включается этот тариф. И здесь Вы правы, надо, конечно, об этом думать. Но обращаю внимание на то, что сегодня у Беларуси 129 долларов за тысячу кубов, в следующем году будет 127, а в ФРГ – 250. И это, безусловно, большое преимущество для наших союзников по Евразэс. Хотя, конечно, мы должны стремиться к полной унификации. Но для этого нужно время и другой уровень интеграции между нашими странами. Но это предмет разговоров, переговоров. Мы к этому процессу готовы. В.Путин: Так и будет, мы же об этом и договорились – создать документы, которые, по сути, являются планом нашего движения к этой цели, «дорожной картой». Просто обращаю внимание на то, что сегодня уже наши партнёры имеют достаточные преимущества. Я упомянул ФРГ не просто так, и в Белоруссии не должно быть 250 за тысячу кубов. Но если бы Белоруссия не имела преимуществ, связанных с интеграцией, а формировали бы цену на рыночных принципах, это было бы не 129 и не 127, а 200 – вот в чём разница. | I15: http://www.kremlin.ru/events/president/news/59319 | J15: 17 | K15: 0 | L15: 7 | M15: 1 | N15: 0 | O15: 12 | P15: 0
A16: Россия | B16: 2019 | C16: 29 мая | E16: Путин | F16: заседание ВЕЭС | G16: Нур-Султан | H16: В.Путин: Уважаемые друзья, коллеги! Я, безусловно, согласен с прозвучавшими в выступлениях оценками работы Евразийского экономического союза за пять лет. Действительно, нам есть ещё над чем работать, мы это и делаем, но, безусловно, сегодня Евразэс – это эффективное интеграционное объединение, деятельность которого строится на принципах равноправия, взаимной выгоды и уважения интересов друг друга. В рамках Союза сформирован, как здесь уже было сказано, общий рынок, охватывающий более 180 миллионов потребителей, обеспечена свобода движения товаров, услуг, капитала, рабочей силы. Интеграционные процессы стимулировали устойчивое развитие экономик наших стран, способствовали повышению качества жизни и благосостояния наших граждан. Отмечу, что по итогам прошлого года, здесь уже некоторые цифры звучали, совокупный ВВП государств Евразэс увеличился на 2,5 процента – до 2,2 триллиона долларов. Прирост промышленного производства в целом по объединению составил 3,1 процента. При этом товарооборот с третьими странами прибавил 18,8 процента, преодолев рубеж в 750 миллиардов долларов. И действительно, он рос у нас даже чуть быстрее, чем объёмы внутренней торговли между участниками объединения: он поднялся на 9,2 процента – до 60 миллиардов долларов. Я, честно говоря, в этом усматриваю тоже позитивный эффект от самого объединения. Потому что объединение, во-первых, это значит, что оно не мешает суверенно развивать свою экономику и контакты с другими странами. Это всё происходит в обычном режиме и, более того, создаёт наиболее благоприятные условия для работы с третьими странами, поскольку создаёт общие, понятные, прозрачные правила взаимодействия, основанные, кстати говоря, на принципах ВТО. Все эти показатели, которые только что были приведены, наглядно свидетельствуют, что евразийская интеграция работает и приносит реальные результаты. Здесь уже говорилось, мы выступили с инициативой наделения Нурсултана Абишевича Назарбаева званием Почётного председателя Высшего евразийского экономического совета, и мне очень приятно, что все коллеги поддержали. И в этом есть смысл, смысл большой. Не только потому, что Нурсултан Абишевич является автором этой идеи и внёс огромный вклад в реализацию самого этого плана, но и потому, что действительно он увлечён этим планом и работает и сейчас и многое ещё может нам сделать полезного для формирования и укрепления нашего Союза. Спасибо, Нурсултан Абишевич, за то, что Вы согласились с этим предложением. Подчеркну, перед Евразэс стоят масштабные задачи по углублению взаимодействия между нашими странами в самых разных отраслях: торговле, финансах, социальной политике. Более слаженных совместных усилий требует унификация законодательной базы в области экономики. На наш взгляд, необходимо продолжить курс на гармонизацию административных правил и процедур, устранение остающихся нетарифных барьеров, облегчение бюрократической нагрузки на бизнес. Предстоит и далее совершенствовать координацию политики государств-объединений в ключевых отраслях экономики. В полной мере осуществить принятые в рамках Евразэс решения о введении наднационального регулирования в банковском и финансовом секторах, в медицине и фармацевтике, транспорте, нефтегазовой промышленности. Здесь у нас ещё есть и споры, и обсуждения, но в целом решения приняты, нужно их только реализовывать. И в энергетике в целом, конечно. В этом контексте большое значение имеет договорённость о формировании общего электроэнергетического рынка Союза, который мы утвердим сегодня. То же самое касается и решения об учреждении Евразийского совета по промышленности. Он займётся выработкой предложений по созданию совместных предприятий с учётом специализации и разделения труда, сложившихся между государствами Евразэс. И здесь, конечно, нам нужно стремиться к тому, о чём Нурсултан Абишевич говорил, и мы можем это сделать, – создание крупных союзных корпораций, думать о целых отраслях производства, распределяя наилучшим образом свои компетенции и взращивая эти компетенции. Серьёзные перспективы для наращивания сотрудничества стран Союза имеются в сфере цифровой экономики. Уже в ближайшее время начнётся осуществление пилотных проектов по маркировке и прослеживаемости товаров, а также организации цифровых транспортных коридоров, которые позволят заметно укрепить и увеличить транзит грузов по таможенной территории Евразэс. Я с пониманием отношусь к той критике, которая и в наш адрес иногда звучит, по поводу предоставления льготных условий для стран, которые не являются членами нашего Союза. Но в условиях развития наших планов в области цифрового обеспечения торговых потоков все эти проблемы будут выстраиваться должным образом. Цифровые технологии в целом призваны обеспечить более тесное взаимодействие по линии малого, среднего бизнеса, выстраивания новых производственных цепочек. Эффективный трансфер технологий, развитие открытой и благоприятной деловой среды – всё это будет более эффективно решаться в рамках «цифры». Для этого в рамках нашего объединения разрабатывается единая информационная база данных о производителях и их продукции. Мы выступаем за то, чтобы евразийская интеграция постепенно охватывала всё новые и новые области, в том числе социальную и трудовую политику. И здесь я не могу не согласиться с Президентом Кыргызстана, это очень важная сфера деятельности. Отмечу подготовку Евразийской комиссией соглашения, которое даст возможность при начислении пенсий учитывать стаж за весь период трудовой деятельности на территории всех государств Союза. Думаю, что для конкретного гражданина, простого человека, который всю жизнь работал, это имеет очень важное значение. Для нас, по большому счёту, и для этого человека будет не важно, где конкретно он работал, главное – чтобы были соответствующие документы, подтверждающие этот стаж. Вступление в силу этого документа позволит в более полном объёме обеспечить права и интересы граждан наших государств. И конечно, особого внимания требуют вопросы, связанные с укреплением системы совместных финансовых институтов Евразэс, призванных поддержать устойчивость экономик стран – участниц объединения, в том числе в периоды нестабильности и на глобальных рынках. В настоящее время Евразийский банк развития финансирует свыше 80 проектов, большая часть из них в области энергетики, транспорта, инфраструктуры, осуществляет инвестиции в жизненно важной для государств Союза сфере. Совокупный объём вложений банка достиг 7,7 миллиарда долларов. Приоритетным направлением деятельности Евразэс является расширение связей с другими государствами, в первую очередь с нашими ближайшими соседями. И, пользуясь присутствием на заседании главы государства – наблюдателя при Евразэс Президента Молдавии Игоря Николаевича Додона и почётного гостя – Президента Таджикистана Эмомали Шариповича Рахмона, хочу воспользоваться их пребыванием, чтобы ещё раз подчеркнуть нашу заинтересованность в углублении взаимодействия Евразэс с представленными ими странами. Выступаем за развитие сотрудничества Союза с динамичными экономиками Азиатско-Тихоокеанского региона. Президент Армении говорил уже о том, что он работал недавно совсем в Пекине с нашими китайскими коллегами и уверен, что такая работа, так же как и работа с ШОС, АСЕАН, другими странами и интеграционными объединениями, безусловно, будет способствовать развитию и осуществлению идеи большого евразийского партнёрства. Стратегическим партнёром нашего Союза, безусловно, является Китай. Это огромная экономика. По паритету покупательной способности Китайская Народная Республика обогнала Соединённые Штаты и стала по объёму экономики первой экономикой мира. Безусловно, это наш сосед, мы должны это учитывать. Мы учитываем это, работаем, тем более что наши процессы в рамках Евразэс вполне стыкуются с идеей Председателя Си Цзиньпина об «Экономическом поясе Шёлкового пути». В ближайшие месяцы вступит в силу соглашение о торгово-экономическом сотрудничестве между Евразэс и КНР, которое станет прочной основой для взаимовыгодной кооперации в самых разных сферах. И вообще круг внешнеторговых партнёров Евразийского союза постоянно расширятся. Сегодня мы примем решение о подписании соглашения о зоне свободной торговли с Сербией. На финальной стадии переговоры по аналогичному документу с Сингапуром, который признан сейчас самой конкурентоспособной экономикой мира. Завершается ратификация временного соглашения с Ираном. Рассчитываем на столь же динамичную работу с Израилем, Египтом, Индией. Как представляется, есть хорошие перспективы и для развития взаимовыгодных контактов Евразэс со странами и интеграционными объединениями Африканского континента. И, уважаемые коллеги, пользуясь случаем, отмечу, что 24 октября в России, в Сочи, пройдёт саммит Россия – Африка. Мы приглашаем руководство Евразийской экономической комиссии принять участие в этом мероприятии. Как известно, сейчас готовится меморандум о взаимодействии Комиссии с Африканским союзом, и этот документ можно было бы подписать на полях сочинской встречи, если, конечно, Комиссия будет к этому готова, а коллеги это всё поддержат. Благодарю за внимание. | I16: http://www.kremlin.ru/catalog/countries/KZ/events/60597 | J16: 23 | K16: 1 | L16: 8 | M16: 0 | N16: 0 | O16: 15 | P16: 0
A17: Россия | B17: 2019 | C17: 1 октября | E17: Путин | F17: заседание ВЕЭС | G17: Ереван | H17: В.Путин: Уважаемые друзья! Согласен с положительными оценками работы Евразийского экономического союза. Евразэс развивается поступательно, создан объёмный общий рынок, который успешно функционирует. Интеграционные процессы в рамках Евразийского союза оказывают самое благоприятное воздействие на рост экономик стран-участниц, способствуют повышению уровня жизни наших граждан. Отмечу, что продолжают расти и совокупные ВВП государств Евразэс, увеличивается промышленное, сельскохозяйственное производство. В то же время перед нашим объединением стоят и новые масштабные задачи. При этом особое внимание, на наш взгляд, следовало бы уделить системной работе по устранению барьеров в торговле товарами и услугами, причём в различных секторах рынка. В числе приоритетов и введение общесоюзного регулирования в финансовой сфере. По итогам текущего заседания имеется в виду утвердить Концепцию формирования общего финансового рынка Евразэс. Этот документ станет «дорожной картой» по разработке и утверждению универсальных правил предоставления банковских и страховых услуг, операций с ценными бумагами. Реализация предусмотренных «дорожной картой» мероприятий позволит упростить доступ граждан наших стран к финансовым инструментам, сделать этот сегмент рынка унифицированным и транспарентным. Хорошими темпами идёт и процесс совершенствования союзного законодательства в сфере энергетики. Рассчитываем, что уже в ближайшее время вступят в силу договорённости по формированию единого электроэнергетического рынка Евразэс. Общее электроэнергетическое пространство должно быть сформировано одновременно с созданием союзных рынков газа, нефти и нефтепродуктов в 2025 году. В первую очередь нужно завершить процесс унификации законодательств государств-членов в сфере поставки и транспортировки газа. Конечно, следует и далее наращивать сотрудничество государств Евразэс в сфере цифровой экономики. В частности, общим интересам отвечает скорейший запуск стандартизированной системы поиска вакансий «Работа без границ». Реализация этого проекта позволит гражданам наших стран узнавать в сети Интернет о свободных рабочих местах во всех государствах союза. Большое значение придаём скорейшей реализации соглашения о прослеживаемости товаров, ввезённых на таможенную территорию Евразэс. Евразийская экономическая комиссия согласно нашему сегодняшнему решению получит соответствующие дополнительные полномочия. Важно обеспечить прозрачность обращения продукции на союзном рынке, поэтому нужно наладить полноценный обмен юридически значимыми электронными сопроводительными товарными документами, а также энергичнее внедрять электронную маркировку товаров. К слову, пилотный проект по маркировке ряда товаров подтвердил эффективность данной меры в борьбе с контрафактной продукцией, увеличил налоговые поступления. Уважаемые коллеги! Считаем важным и далее проводить работу, направленную на укрепление взаимовыгодного экономического сотрудничества Евразэс с заинтересованными зарубежными партнёрами. И конечно, я так же, как и другие коллеги, приветствую здесь сегодня и Президента Молдавии Игоря Николаевича Додона, Президента Ирана господина Хасана Рухани, Премьер-министра Сингапура господина Ли Сянь Луна. Подчеркну, что подписываемое сегодня в присутствии господина Ли Сянь Луна соглашение о зоне свободной торговли с Сингапуром создаст благоприятные условия для наращивания встречных экспортно-импортных операций, углубления кооперации в самых разных сферах. Совсем недавно я имел удовольствие быть по приглашению правительства в Сингапуре. Должен сказать и подтвердить, что, конечно, Сингапур – это надёжный, устойчивый партнёр с быстро развивающейся экономикой и хорошим административным регулированием. Ожидаем также, что в конце октября вступит в силу временное соглашение, ведущее к образованию зоны свободной торговли между Евразэс и Ираном. Его реализация приведёт к значительному снижению импортных тарифов, отмене других ограничений, мешающих движению товарных потоков. Всё это, несомненно, будет способствовать росту взаимной торговли и инвестиций. Вообще, география контактов нашего союза постоянно расширяется. Объединение ведёт предметные переговоры о сотрудничестве с 13 странами и более чем 20 международными структурами и организациями. Это и Сербия, и Израиль, Египет. Вскоре стартуют аналогичные переговоры по зоне свободной торговли с Индией с её колоссальным, огромным рынком – быстро развивающаяся экономика, по темпам сегодня она номер один в мире. В привязке к саммиту Россия–Африка – хочу вас проинформировать об этом, уважаемые коллеги, 23–24 октября в Сочи пройдёт впервые саммит Россия–Африка – Евразийская экономическая комиссия намерена подписать меморандум о взаимопонимании с комиссией Африканского союза, направленный на развитие многостороннего сотрудничества «пятёрки» со странами Африканского континента. Евразэс уже давно и плодотворно расширяет взаимодействие с динамичными экономиками Азиатско-Тихоокеанского региона. Необходимо и далее налаживать тесные связи Евразийского союза с Шанхайской организацией сотрудничества и АСЕАН, работать в пользу большого евразийского партнёрства. Особую роль в этом контексте играют торгово-экономические отношения Евразийского экономического союза с Китаем, который, кстати, сегодня отмечает большой праздник – 70‑летие образования Китайской Народной Республики. Я от имени России хочу поздравить наших китайских друзей с этим событием. Мы убеждены, что скорое вступление в силу соглашения о сотрудничестве с КНР станет шагом на пути сопряжения интеграционных процессов в рамках Евразэс с китайской инициативой «Один пояс, один путь». И в заключение, уважаемые коллеги, хотел бы поблагодарить наших армянских коллег и друзей за организацию нашей сегодняшней совместной работы. Благодарю вас за внимание. | I17: http://www.kremlin.ru/events/president/news/61682 | J17: 17 | K17: 0 | L17: 7 | M17: 0 | N17: 0 | O17: 11 | P17: 0
A18: Россия | B18: 2019 | C18: 20 декабря | E18: Путин | F18: заседание ВЕЭС | G18: Санкт-Петербург | H18: В.Путин: Уважаемые коллеги, друзья! Хочу вас искренне, сердечно поприветствовать в Петербурге. Как и договаривались, мы встречаемся в очередной раз в преддверии Нового года. Поэтому надеюсь, что наша сегодняшняя работа будет конструктивной, предпраздничной и будет отвечать нашему настроению. Оно заключается в том, чтобы двигаться дальше и как можно основательнее, как можно быстрее в направлении реализации всех наших планов. Сейчас не буду перечислять все плюсы, которые мы получили от взаимной работы на протяжении нескольких лет. Хочу ещё раз поблагодарить нашего почётного председателя Нурсултана Абишевича Назарбаева, который в своё время выступил инициатором создания этого объединения. Нурсултан Абишевич, всё функционирует у нас, функционирует самым наилучшим образом. Мы очень рады Вас приветствовать в этом качестве сегодня в Петербурге. Хочу обратить внимание на то, что есть вопросы, которые, конечно, ещё подлежат решению, это связано с различного рода ограничениями, изъятиями. В этой связи отмечу, что в принципе это характерно для любых экономических интеграционных объединений. Мы с вами постепенно, но двигаемся в направлении снятия этих ограничений по мере готовности наших стран к тем или иным шагам. У нас должна быть в ближайшее время выработана – и она, собственно, уже почти выработана, – согласована в окончательном виде стратегия нашего развития. Думаю, что и этому вопросу – по сути, это вопрос стратегического характера – мы уделим сегодня необходимое внимание, так же как и выборам руководства нашей комиссии, исполнительного органа нашего союза. На этот раз его в соответствии с принципом ротации должен возглавить представитель Белоруссии. Мы сегодня тоже об этом поговорим и соответствующее решение должны принять. Я вас всех ещё раз приветствую. Хорошего вам пребывания в Петербурге. Надеюсь на успешную рабочую встречу сегодня. | I18: http://www.kremlin.ru/events/president/transcripts/62375 | J18: 0 | K18: 0 | L18: 1 | M18: 0 | N18: 0 | O18: 2 | P18: 0
A19: Россия | B19: 2020 | C19: 14 апреля | E19: Путин | F19: заседание ВЕЭС | G19: онлайн | H19: В.Путин: Прежде всего хочу присоединиться к словам благодарности нашим белорусским друзьям за инициативу провести сегодняшнее мероприятие. Согласен со многими прозвучавшими сейчас оценками. Пандемия коронавируса оказывает действительно негативное влияние на все стороны жизни, причём практически во всём мире, на экономику, социальную сферу, снизилась мобильность населения, затруднена торговля товарами и услугами, подвержены волатильности глобальные финансовые и – только что об этом говорил Президент Казахстана – сырьевые рынки, для нас это очень важно. Существенно возрастает нагрузка на систему здравоохранения, требуются действительно экстраординарные меры, чтобы остановить распространение инфекции. Как мы видим, в некоторых наших странах принимаются действительно чрезвычайные меры. Ещё раз скажу, Президент Казахстана только что об этом сказал. Понятно, что эффективно противостоять пандемии можно только путём объединения усилий международного сообщества. Именно такие, коллективные подходы Россия продвигает на всех многосторонних площадках: и в ООН, и в «Группе двадцати», и в СНГ. И, конечно же, считаем крайне востребованным тесное сотрудничество между государствами Евразэс. Поддерживаем подготовленный для нашего утверждения проект совместного заявления лидеров «пятёрки». Полагаем, что в нём в полной мере отражены подходы к организации дальнейшей работы в рамках Союза в условиях распространения коронавирусной инфекции. Несколько слов о том, какие мероприятия реализуются в России для борьбы с коронавирусом и минимизации последствий пандемии для экономики. Созданы и активно действуют координационный совет во главе с Правительством России, оперативный штаб по предупреждению завоза и распространения вируса, рабочая группа Госсовета, которая координирует работу в регионах. По оценкам экспертов, пик заболеваемости в России ещё не пройден. На 13 апреля в России зафиксировано 18 328 случаев заражения. К сожалению, из жизни ушли 148 человек. Вылечились 2558. Мы внимательно следим за санитарно-эпидемиологической обстановкой, проводим необходимые профилактические и другие мероприятия, чтобы сдержать распространение инфекции. В большинстве российских регионов введён режим самоизоляции или карантина для снижения темпов эпидемии. До 30 апреля по всей стране установлены нерабочие дни с сохранением заработной платы. Увеличиваются объёмы диагностики и тестирования для выявления заболевших и носителей вируса. Значительные финансовые ресурсы направлены на развёртывание оснащённых специальным оборудованием инфекционных блоков в больницах, на закупку медицинского оборудования и техники. По линии Минобороны ведётся строительство 16 специализированных госпиталей для размещения пациентов с коронавирусной инфекцией, которые будут сданы в ближайшее время. И, разумеется, ими будут пользоваться при необходимости не только военнослужащие, но и гражданские лица. Принято решение о дополнительных выплатах медперсоналу, который, рискуя жизнью и здоровьем, помогает больным, достойно исполняет свой служебный долг. Поддержка оказывается и гражданам. Прежде всего семьям с детьми, временно безработным, тем, кто столкнулся с существенным – это более чем 30 процентов – сокращением доходов. Им предоставляются каникулы, отсрочки по ипотеке. Общий объём средств, выделяемых Правительством на минимизацию негативных последствий эпидемии, достигает 1,2 процента ВВП. Такой же объём содействия предусмотрен и Центральным банком России. Реализован и ряд серьёзных мер в сфере банковского регулирования и финансов, в том числе в целях повышения доступности заёмных средств для поддержки регионов, сталкивающихся с падением налогового дохода. Одновременно для недопущения оттока капитала увеличена до 15 процентов налоговая ставка на доход, выведенный на зарубежные счета. Целевая помощь оказывается предприятиям, прежде всего тем, которые сохраняют занятость, малому и среднему бизнесу. На шесть месяцев предоставлена отсрочка по налогам, страховым платежам, упрощены административные процедуры получения лицензионных и разрешительных документов. И это не всё. Мы, разумеется, думаем над следующими шагами поддержки экономики. Конечно, многое делается для того, чтобы вернуть граждан России, оказавшихся в разгар эпидемии за границей. В этой работе задействованы наши авиационные компании, организуются специальные чартерные рейсы. Вернувшиеся помещаются на карантин. Материальная поддержка оказывается и тем, кто всё ещё ждёт вылета на родину, находится за границей. Мы не остаёмся безучастными и к проблемам, с которыми из-за пандемии сталкиваются другие государства, стараемся помочь прежде всего остро нуждающимся странам. Продолжим, безусловно, эту работу, будем делиться полученным опытом, обмениваться оперативной информацией. Здесь уже отмечалось, что Россия очень активно работает над лекарствами, специальными средствами для борьбы с пандемией, над вакцинами. Действительно, работа идёт хорошо. И я надеюсь, что мы в ближайшее время сможем с вами поделиться полученными результатами. Хотел бы особо отметить антикризисную работу, которая развёрнута по линии Евразийского экономического союза. В прошлую пятницу состоялось заседание межправсовета с участием премьер-министров. Приняты принципиальные решения, направленные на минимизацию последствий распространения коронавируса, поддержание стабильной социально-экономической обстановки в наших государствах. Для импорта на территорию Евразэс социально значимых товаров – продовольствия, лекарств, медицинского оборудования, средств индивидуальной защиты – открыт зелёный коридор. Согласен с теми коллегами, которые сказали о том, что надо подумать над расширением этой практики. То есть такие товары освобождены от ввозных таможенных пошлин, упрощены и ускорены соответствующие таможенные процедуры. Правительства государств Союза условились сообща принимать меры по ограничению вывоза в третьи страны критически важных медицинских препаратов и техники, социально значимых товаров, с тем чтобы не допустить их нехватки на союзном рынке, если возникнет необходимость помогать друг другу с доставкой гуманитарной помощи, товаров первой необходимости. Стоит подумать о том, чтобы снизить или обнулить таможенные пошлины на комплектующие и материалы для экономически и социально значимых отраслей, в целом поддержать промышленное производство наших стран, те сектора экономики, которые в наибольшей степени пострадали в условиях эпидемии. Речь идёт прежде всего о воздушном транспорте, туризме, гостиничном бизнесе, сфере развлечений и досуга, общественного питания, культуры и спорта. Созданный по линии Евразийской экономической комиссии координационный совет по борьбе с пандемией в режиме реального времени отслеживает обстановку в Евразэс, оценивает потребности и возможности государств-членов по поставкам критически важных товаров. Согласен, что в случае необходимости можно привлечь и ресурсы Евразийского фонда стабилизации и развития и Евразийского банка развития. Не могу не согласиться и с тем, что методы борьбы с пандемией должны быть разумными и пропорциональными, не приводить к разрыву наработанных десятилетиями кооперационных связей, остановке международной торговли, прекращению взаимных инвестиций. Уже сейчас в рамках Евразэс нужно начать разработку мер системного характера, призванных создать условия для восстановления и обеспечения дальнейшего экономического развития. Речь идёт, в частности, о том, чтобы активизировать процесс цифровизации в сфере логистики, об этом уже тоже говорилось, таможенных и налоговых процедур. В целях сохранения макроэкономической устойчивости востребовано взаимодействие Центробанков государств-членов по вопросам смягчения параметров кредитования предприятий реального сектора экономики, расширения безналичных и «быстрых» платежей, дистанционного получения банковских услуг. Как известно, к очередному заседанию Высшего совета, которое запланировано на 19 мая, готовится проект стратегических направлений развития Евразийской экономической интеграции до 2025 года. Предложил бы с учётом приобретаемого в условиях пандемии опыта усилить положения документа, которые касаются сотрудничества в области здравоохранения, оценить, насколько имеющиеся механизмы адекватны и позволят нам в будущем, в случае повторения подобных критических ситуаций, действовать более оперативно, более слаженно и с большей отдачей. И в заключение хотел бы попросить Александра Григорьевича Лукашенко как Председателя Высшего Евразийского экономического совета проинформировать наших коллег по СНГ, председательствующих сейчас в Содружестве узбекских партнёров об итогах сегодняшней встречи, предпринимаемых странами Евразийского союза усилиях по борьбе с распространением коронавируса, подчеркнув нашу готовность к совместной работе со всеми партнёрами по СНГ. Благодарю вас за внимание. | I19: http://www.kremlin.ru/events/president/news/63199 | J19: 11 | K19: 0 | L19: 9 | M19: 1 | N19: 0 | O19: 13 | P19: 0
A20: Россия | B20: 2020 | C20: 19 мая | E20: Путин | F20: заседание ВЕЭС | G20: онлайн | H20: «Уважаемые коллеги, добрый день ещё раз! Вы уже отмечали, что мы живём в непростые времена, можно сказать, сложные, связанные с пандемией. Это всё напрямую отражается на нашем взаимодействии, отражается на экономике, на прямых контактах между людьми, а это создаёт известные трудности и в реализации нашей совместной повестки дня. И тем не менее Беларусь, которая председательствует сейчас в нашей организации, находит возможности активно, я хочу это подчеркнуть, активно продолжать нашу совместную работу. Хочу поблагодарить Президента Белоруссии, это уже второе мероприятие, которое проводится. 14 апреля уже было подобное мероприятие, была видеоконференция членов Высшего Евразийского экономического совета, комиссия работает активно с представителем Белоруссии тоже, мне кажется, это хороший пример для подражания. Разумеется, все мы заинтересованы в том, чтобы обеспечить динамичное развитие нашего объединения. Оно работает уже более пяти лет, приносит ощутимую отдачу всем нашим государствам, способствует решению важнейших задач по развитию национальных экономик, повышению уровня жизни наших граждан. Именно на дальнейшее углубление разностороннего сотрудничества в рамках «пятёрки» ориентирован подготовленный к сегодняшнему заседанию проект Стратегии развития евразийской экономической интеграции на перспективу до 2025 года. В нём ставятся комплексные задачи по завершению формирования общего рынка товаров, услуг, капитала и рабочей силы, совершенствованию таможенного и административного регулирования, формированию цифрового пространства. Коллеги тоже об этом говорили, присоединяюсь, это очень важное направление. Имеется в виду также выстроить систему управления совместными кооперационными проектами в высокопроизводительных секторах экономики. Стратегия закладывает основу для активизации процессов импортозамещения, промышленной локализации и продвижения совместных инициатив с высокой интеграционной составляющей. В наших странах должны быть созданы новые производственные мощности, обеспечивающие продовольственную безопасность, выпуск товаров первой необходимости, другой критически важной продукции. Стратегия предусматривает расширение сотрудничества государств – членов Евразэс в научно-технической и гуманитарной областях. Предполагается реализация крупных совместных проектов в сфере профессионального и университетского обучения, подготовки кадров, повышения академической мобильности и осуществления многосторонних образовательных программ. Конечно, столь масштабные планы по развитию Евразийского экономического союза на период до 2025 года требуют от всех государств-членов ещё более активного взаимодействия и плотной координации. Но в целом, на наш взгляд, получился действительно масштабный документ, определяющий курс Евразийского экономического союза на ближайшую и среднесрочную перспективу. Его принятие создаст надёжную основу для углубления интеграции, дальнейшего сближения наших экономик и расширения областей нашего сотрудничества. Проект практически согласован, за исключением одного пункта, касающегося тарифов на транспортировку газа. Предыдущий выступающий, Президент Кыргызстана, об этом тоже упомянул. Имеется в виду формула, которую поддерживают три страны – Россия, Казахстан и Киргизия. Её суть в том, что подходы к ценообразованию на газ можно было бы определить позднее на переговорах по формированию общего рынка газа Евразэс. Эту формулу пока не принимают наши армянские и белорусские коллеги, у них своя точка зрения по этому вопросу. Если бы они смогли согласиться с ней, то других препятствий на пути одобрения Стратегии не осталось бы вообще. Что касается предлагаемого нашими армянскими и белорусскими друзьями единого тарифа на услуги по транспортировке и транзиту газа, то мы считаем, что единый тариф может быть реализован лишь на едином рынке с единым бюджетом, единой системой налогообложения. Столь глубокий уровень интеграции в Евразэс пока ещё не достигнут, мы об этом с вами хорошо знаем, а пока цены на газ должны формироваться на основе рыночной конъюнктуры, учитывать затраты и инвестиции поставщиков, а также обеспечивать обоснованную норму прибыли на вложенный в добычу капитал. Это обычная, хочу подчеркнуть, уважаемые коллеги, обычная мировая практика. Если позиции наших армянских и белорусских друзей останутся без изменений, то, наверное, было бы логично вообще исключить пункт по газу из проекта Стратегии, чтобы одобрить её сегодня. Обсуждение же подходов к ценообразованию на газ можно будет продолжить по линии экспертов государств – членов Евразийской экономической комиссии. Кстати, на неё возлагается особая ответственность за работу по реализации планируемых нами стратегических задач. Для этого необходимо укрепить организационную роль комиссии, усилить её ответственность в том числе за реализацию принимаемых Высшим Евразийским экономическим советом решений. Считаем также целесообразным энергичнее подключать к деятельности Евразийской экономической комиссии Евразийский банк развития и Евразийский фонд стабилизации. Эти региональные финансовые механизмы могут и должны оказывать содействие осуществлению крупных совместных интеграционных проектов. Конечно же, важно и далее проводить работу, направленную на укрепление взаимовыгодного экономического сотрудничества Евразэс с заинтересованными зарубежными партнёрами. С союзом уже установили тесные прямые контакты многие государства и интеграционные структуры, и их круг постоянно растёт. В активе Евразэс международные соглашения с Китаем, Вьетнамом, Ираном, Сербией, Сингапуром, на продвинутом этапе находится переговорный процесс с Израилем и Египтом, запущены торговые консультации с Индией. Конечно, стоит уделять первостепенное внимание поддержанию различных форматов диалога и с другими партнёрами, прежде всего по СНГ, расширять связи с Ассоциацией государств Юго-Восточной Азии и Шанхайской организацией сотрудничества. Убеждён, что совместная работа с этими крупнейшими региональными объединениями, а также продолжение усилий по сопряжению деятельности Евразэс с реализацией китайской инициативы «Один пояс, один путь» позволит в перспективе реализовать проект создания большого евразийского партнёрства. Перед нашим объединением стоят действительно большие, масштабные задачи. Много предстоит сделать для того, чтобы окончательно победить эпидемию коронавирусной инфекции, восстановить рост экономики, решить вопросы, связанные с социальными проблемами. Разумеется, Россия будет в постоянном контакте со всеми нашими коллегами и друзьями. Мы найдём способ активно работать, так, как это сделала Белоруссия. Ещё раз хочу подчеркнуть: Россия заинтересована в развитии нашего объединения. Хочу поблагодарить всех коллег за сегодняшнюю совместную работу и выразить слова благодарности Президенту Белоруссии Александру Григорьевичу Лукашенко. Спасибо большое». | I20: https://e-gorod.ru/саммит-еаэс-19-мая-2020-видеоформат-выступл/ | J20: 16 | K20: 1 | L20: 5 | M20: 0 | N20: 0 | O20: 8 | P20: 0
A21: Россия | B21: 2020 | C21: 11 декабря | E21: Путин | F21: заседание ВЕЭС | G21: онлайн | H21: В.Путин: Уважаемый Александр Григорьевич! Уважаемые друзья! Прежде всего хотел бы присоединиться к прозвучавшим здесь словам благодарности в адрес белорусского руководства за проделанную работу в ходе председательства в Евразийском экономическом союзе в 2020 году. Несмотря на то что эта работа велась в непростых условиях, связанных с распространением пандемии коронавируса, нам вместе удалось всё-таки многого добиться, интеграционные процессы в рамках Евразэс продолжали успешно развиваться. Об этом свидетельствует и солидный пакет решений и договорённостей, подготовленных для утверждения на сегодняшнем заседании Высшего Евразийского экономического совета. Убеждён, что их реализация будет способствовать дальнейшему расширению взаимодействия в торговле, в инвестициях, экономике в целом, финансах, в промышленности и энергетике, да и во всех других сферах. Уже отмечалось, что государства «пятёрки» оперативно наладили эффективное сотрудничество в борьбе с коронавирусом, а принятый в июле совместный план мероприятий, направленный на укрепление систем здравоохранения стран Евразэс и предотвращение распространения инфекции, выполняется в полном объёме. Что касается России, то мы передали партнёрам по союзу тест-системы для проведения в общей сложности свыше 900 тысяч исследований на COVID-19, поставляем и продолжим поставлять медикаменты, средства индивидуальной защиты, расходные материалы. Очень важно, что, как вы знаете, российские специалисты находятся в постоянном контакте с коллегами из стран «пятёрки», оказывают консультативную помощь, делятся опытом. В наиболее пострадавшие районы государств Евразэс выезжали наши бригады врачей-эпидемиологов, направлялись мобильные лаборатории. Сейчас прорабатывается вопрос о поставках в страны союза российской вакцины «Спутник-V». Кстати, у нас уже прошла регистрацию вторая вакцина – «ЭпиВакКорона», и ещё одна находится на завершающей стадии испытаний. И мы, конечно же, заинтересованы в том, чтобы все партнёры по «пятёрке» приняли участие в научных и клинических исследованиях российской вакцины, в организации совместного производства. Пандемия коронавируса, к сожалению, оказала негативное влияние на положение дел в экономике и социальной сфере наших государств. Наблюдается спад валового внутреннего продукта, объёмов торговли, промышленного производства. Всё это сказывается и на уровне занятости и безработицы. Поэтому перед всеми нами, перед всеми странами Евразэс наряду с заботой о жизни и здоровье людей, конечно, в числе приоритетов стоит и задача сделать так, чтобы нынешние экономические неурядицы не приобрели затяжной и долгосрочный характер. И это побуждает нас ещё больше сплотиться, ещё более энергично заниматься выправлением ситуации, решением вопросов экономического восстановления и развития, активнее продвигаться по пути интеграционного строительства. Мы поддерживаем подготовленный правительствами «пятёрки» проект стратегических направлений развития евразийской интеграции до 2025 года, предусматривающий завершение формирования в рамках Евразэс общего рынка товаров, услуг, капитала, рабочей силы, а также единого цифрового пространства. Всё это нацелено на то, чтобы стимулировать рост экономик наших государств и в конечном итоге повысить благосостояние и качество жизни наших граждан – собственно говоря, в этом состоит наша основная цель. Отдельно хотел бы остановиться на вопросах сотрудничества государств – членов Евразэс в сфере цифровизации. Мы все в этом году воочию убедились, насколько важное значение с учётом возникших обстоятельств имело использование передовых информационных технологий. Во многом благодаря этому удалось обеспечить нормальное функционирование государственных органов, буквально всех отраслей промышленности, образования, медицины. Подчеркну, что Россия была одним из инициаторов развития взаимодействия на данном направлении. Мы с удовлетворением отмечаем, что принятая в 2017 году на саммите Высшего Евразийского экономического совета в Сочи цифровая повестка союза последовательно реализуется. Она предусматривает проведение государствами «пятёрки» согласованной политики в области развития интернет-экономики, формирование общих правил электронной торговли, единых стандартов обмена информацией и её защиты. В рамках Евразэс уже осуществляются крупные цифровые проекты в сфере транспорта, промышленности, рынка труда. Продвижением цифровых инициатив занимается, как известно, Евразийский банк развития. По его линии учреждён и специальный фонд, призванный содействовать финансированию новых перспективных проектов в сфере информационной интеграции. Один из таких проектов предложен Россией и подразумевает создание мобильного приложения, позволяющего значительно упростить административные формальности при передвижении между странами Евразэс. Электронные технологии помогают и в деле защиты нашего общего рынка и, соответственно, потребителей от контрафактной продукции. Мы нацелены на ограничение нелегального товарооборота, улучшение конкурентной среды для бизнеса, для наших с вами предприятий. Используемые в рамках Евразэс цифровые механизмы маркировки товаров, применение которых, напомню, также было инициировано Россией, помогают обеспечить контроль за перемещением грузов по территории союза. Представляется полезным расширить сферу действия соглашения о маркировке товаров. До конца года будут внедрены цифровые метки для маркировки табачных изделий, некоторых лекарственных препаратов, парфюмерии, обуви, фотооборудования, автомобильных шин. С 1 января 2021 года предусматривается введение маркировки товаров лёгкой промышленности, а затем и отдельных видов молочной продукции. Уважаемые коллеги, друзья! Хотел бы отметить, что развивающаяся интеграция в рамках Евразэс вызывает заинтересованное внимание целого ряда зарубежных государств, мы уже об этом говорили. Сегодня Высший Евразийский экономический совет примет решение о предоставлении Республике Узбекистан – приветствую нашего коллегу Президента Узбекистана – и Республике Куба – тоже разрешите поприветствовать Президента Кубинской Республики – статуса наблюдателя. Это действительно важный качественный шаг по укреплению связей союза с нашими естественными, традиционными партнёрами. Реализуется соглашение о сотрудничестве Евразэс с такими крупными экономическими странами, как Китай, Индия – в ближайшее время состоится первый раунд переговоров по соглашению о свободной торговле с Индией. А сегодня утвердим решение о запуске аналогичных переговоров с Ираном. Мы также поддерживаем идею заключения преференциальных договорённостей с Индонезией и Монголией. Стоит особо отметить, что 10 ноября в ходе прошедшего под российским председательством заседания совета глав государств Шанхайской организации сотрудничества был подписан Меморандум о взаимопонимании между Секретариатом ШОС и Евразийской экономической комиссией. Видим в этом ещё один шаг на пути к осуществлению выдвинутой нами идеи создания большого евразийского партнёрства в сфере безопасности, экономического и гуманитарного взаимодействия. В этом контексте, конечно, большое значение имеет развитие сотрудничества с другими странами и региональными интеграционными объединениями. В первую очередь речь идёт о сопряжении деятельности Евразэс с реализацией китайской известной инициативы «Один пояс, один путь». В конечном итоге упомянутые мной шаги, несомненно, сыграют свою положительную роль для формирования на всём пространстве нашего общего евразийского континента по-настоящему благоприятной атмосферы партнёрства и сотрудничества. Уважаемые коллеги! В заключение хотел бы пожелать нашим казахстанским друзьям, которые будут принимать председательство в Евразийском союзе, успехов в будущем году. Можете, безусловно, уважаемые коллеги, рассчитывать на нашу поддержку, на всемерное содействие с нашей стороны. Не сомневаюсь, что Казахстан, поскольку он является инициатором создания нашего объединения – и я хочу ещё раз вспомнить о роли первого Президента Казахстана Нурсултана Абишевича Назарбаева в этом, хочу его поблагодарить за эту идею и за то, что продвигал её на постсоветском пространстве, причём достаточно энергично и эффективно, – не сомневаюсь в этой связи, что казахстанское председательство будет успешным. Благодарю вас за внимание. | I21: http://www.kremlin.ru/events/president/news/64643 | J21: 22 | K21: 0 | L21: 3 | M21: 1 | N21: 0 | O21: 16 | P21: 2
A22: Россия | B22: 2021 | C22: 10 декабря | E22: Путин | F22: заседание ВЕЭС | G22: онлайн | H22: В.Путин: Уважаемый Касым-Жомарт Кемелевич! Уважаемые коллеги, друзья! Я тоже, как и все, присоединяюсь к словам благодарности в адрес наших казахстанских друзей за проделанную работу в ходе председательства в Евразийском экономическом союзе в этом году. Подчеркну: я видел, знаю, как Президент Республики [Казахстан] лично вовлечён в эту работу, уделяет этому много своего времени. Несмотря на сложные условия, связанные с пандемией коронавируса и волатильностью на глобальных рынках, взаимодействие в рамках Евразэс развивалось весьма продуктивно. Действительно, хочу ещё раз подтвердить то, что было сказано только что нашим казахстанским коллегой: первый Президент Казахстана Нурсултан Абишевич Назарбаев был инициатором создания нашего объединения. Прекрасно помню о его телефонном звонке, когда он позвонил и задал ряд сакраментальных, так бы сказал, вопросов по поводу того, что Россия видит в качестве приоритетов на ближайшее будущее. И договорились, что таким приоритетом и для Казахстана, и для России будет создание интеграционного объединения, о котором мы говорили раньше и к которому были готовы присоединиться и Белоруссия и, кстати говоря, Украина тогда. Но с Украиной не получилось, хотя такие намерения были высказаны тогдашним руководством Украины. Тем не менее с лёгкой руки первого Президента Казахстана этот процесс начал развиваться, и сегодня мы чувствуем, что это было сделано абсолютно правильно – в этот сложный период времени для всей мировой экономики и для нашей экономики тоже. Мы видим, что совместными усилиями удалось также нарастить взаимную торговлю, несмотря ни на какие трудности. За девять месяцев текущего года объём товарооборота между государствами – членами союза – Касым-Жомарт Кемелевич сказал, по их данным, где-то на 16 процентов вырос, – по нашей статистике, на 10 процентов превысил аналогичный показатель доковидного, 2019 года. Это хороший показатель в любом случае. Устойчивую динамику демонстрируют встречные инвестиции, финансовый сектор и рынок труда. Хотел бы также с удовлетворением отметить, что продолжается процесс совершенствования общего законодательства Евразийского союза. Оно приводится в соответствие с новыми масштабными задачами интеграционного строительства. Министерства и ведомства экономического блока наших стран вместе с Евразийской экономической комиссией активно занимаются выявлением и устранением препятствий на пути свободного движения товаров, услуг, капиталов, рабочей силы – то, о чём сказал сегодня в своём выступлении первый Президент Казахстана. Сегодня на данном направлении будут сделаны очередные серьёзные шаги – существенный шаг вперёд в связи с подготовленным и выносимым на наше одобрение солидным пакетом поправок к Договору о Евразийском экономическом союзе. Цель этих поправок – заполнить имеющиеся лакуны и пробелы в правовом регулировании хозяйственно-экономической деятельности на пространстве Евразэс. Россия непосредственно участвовала в разработке этих поправок, и, безусловно, мы поддерживаем их принятие. Также поддерживаем проекты совместных документов, касающихся дальнейшего развития единого рынка услуг, в том числе в таких секторах, как строительство, аудиторская и оценочная деятельность. Кроме того, сегодня на наше утверждение вынесено подготовленное по инициативе России соглашение о применении в Евразэс электронных навигационных пломб – хочу ещё раз вернуться к тому, что мы обсуждали несколько лет назад, – они позволяют отслеживать – действительно, согласен с коллегами, которые сейчас только об этом сказали, – трансграничные перевозки грузов, надёжно гарантировать сохранность товаров и упростить процедуры их оформления на границе. Кстати сказать, это в значительной степени снижает озабоченности многих других стран, которые присматриваются к работе нашего объединения и являются сегодня наблюдателями. Использование таких пломб, безусловно, повысит транспарентность таможенных операций, позитивно скажется на развитии сектора транспортных услуг на территории Евразэс. Об этом только что коллега из Кыргызстана сказал, полностью с ним согласен. И, что немаловажно, сделает более привлекательными наши транспортные маршруты для транзитных перевозок грузов между Европой и Азиатско-Тихоокеанским регионом. У России имеется и ряд других предложений по обеспечению прозрачности рынков товаров и услуг Евразэс, и мы надеемся на их поддержку со стороны партнёров по интеграции. В частности, речь идёт о более широком внедрении механизмов маркировки товаров, которые уже успешно применяются для отдельных товарных позиций. Эта практика показала свою эффективность в решении таких задач, как борьба с нелегальным товарооборотом, особенно в потребительском секторе, увеличение налоговых поступлений в бюджеты стран-участниц, создание конкурентоспособной среды для бизнеса. Российская сторона также последовательно выступает за дальнейшее расширение в рамках Евразэс взаимовыгодной промышленной кооперации, о чём говорил сегодня Президент Белоруссии. В текущем году утверждены комплексная стратегия промышленного сотрудничества стран – членов Евразэс и «дорожная карта» по её реализации. Эти взаимодополняющие документы закладывают фундамент для углубления кооперационных связей между производственными предприятиями наших государств и ускорения в рамках союза процесса импортозамещения. Борьба с коронавирусной инфекцией стимулирует наши страны к более тесному партнёрству в фармацевтической индустрии и в целом в области медицины. Я помню, как Премьер-министр Армении был инициатором разворачивания нашей совместной работы по этому направлению и даже предлагал целую программу в этой связи. Собственно говоря, мы её сейчас и осуществляем. В соответствии с поручением, которое мы дали в рамках нашего заседания в декабре прошлого года, в большинстве государств Евразэс успешно налажен выпуск российских вакцин. При этом хочу подчеркнуть: Россия не только инвестировала в создание производственных мощностей и новых рабочих мест, но и осуществила трансфер самых современных биомедицинских технологий. Таким образом, наши партнёры по Евразэс смогли увеличить темпы вакцинации населения высокоэффективными препаратами – собственного производства, хочу подчеркнуть. Благодаря этому повышается коллективный иммунитет к COVID-19 на всём евразийском пространстве. А это важно в плане создания условий для полноценного возобновления свободного перемещения граждан наших стран по территории союза. Решению задачи восстановления мобильности населения в условиях пандемии помогает и реализация другого совместного проекта в области инноваций и информационных технологий, имею в виду мобильное приложение для смартфонов «Путешествую без COVID-19». Кстати, помимо государств Евразэс оно используется и в других странах: в Азербайджане, Молдавии, Таджикистане и Узбекистане. Мы предлагаем продолжить работу по улучшению функционала и расширению географии применения этого приложения. Есть и другие весьма актуальные и важные сферы, в которых следует нарастить сотрудничество государств – членов Евразэс. Это касается, например, взаимодействия по климатической повестке и тематике «зелёной» трансформации экономики. Коллеги только что тоже об этом говорили. К слову, по инициативе России сформирована специальная рабочая группа высокого уровня, которая занялась координацией наших позиций по вопросам борьбы с выбросами парниковых газов и достижения углеродной нейтральности, сохранения окружающей среды. И мы рассчитываем на дальнейшую конструктивную совместную работу с партнёрами по Евразэс по этой тематике. Я знаю, что все вы, уважаемые коллеги, вовлечены так или иначе в эту работу. Предлагаю действовать более слаженно и более энергично по этому направлению. С удовлетворением отмечу, что к деятельности Евразийского союза всё активнее подключаются государства-наблюдатели – здесь тоже об этом было сказано, я приветствую от всей души наших коллег: это Куба, Узбекистан, кстати говоря, и Молдавия проявляла к этому тоже в своё время интерес. Они имеют возможность участвовать в деятельности интеграционных органов на всех уровнях, знакомиться с процессом подготовки интеграционных документов и использования в своих целях принятых решений. Мы знаем, как сейчас складывается энергетическая ситуация в Европе. Молдавия была бы поближе к решению некоторых вопросов и легче бы, наверное, решала те проблемные вопросы, которые возникают, была бы хотя бы в курсе происходящих событий и принимаемых нами решений. Но мы договорились, исходя из общих интересов решили эти вопросы, но в целом это совершенно очевидный факт: были бы в материале, легче было бы решать вопросы, о которых мы говорим. Кроме того, развивающаяся в рамках Евразэс интеграция привлекает заинтересованное внимание и других зарубежных государств. В частности, налажена гибкая система связей нашего союза со странами ‒ членами таких интеграционных объединений, как Шанхайская организация сотрудничества и АСЕАН. Действительно, ведутся переговоры с Ираном о заключении полноформатного соглашения о свободной торговле, сегодня тоже об этом говорилось. С этой страной согласовано и продление действующего временного соглашения – на три года или до вступления в силу постоянного соглашения о свободной торговле. Реализация этого документа даст хорошие результаты, я в этом нисколько не сомневаюсь. Вообще, подчеркну, что Россия всячески приветствует активизацию международных деловых связей и контактов Евразийского союза, выступает за дальнейшее расширение спектра преференциальных и непреференциальных соглашений с зарубежными государствами. И мы, конечно, поддерживаем представленный проект решения на этот счёт. С учётом сказанного отмечу, что перед нашими киргизскими друзьями, которые будут председательствовать в Евразийском союзе в следующем году, встают по-настоящему серьёзные и ответственные задачи. Безусловно, Кыргызстан может рассчитывать на всемерное содействие со стороны России. Хочу поблагодарить вас за внимание. Спасибо большое. | I22: http://www.kremlin.ru/events/president/news/67334 | J22: 21 | K22: 1 | L22: 8 | M22: 0 | N22: 0 | O22: 13 | P22: 0
A23: Россия | B23: 2021 | C23: 14 октября | E23: Путин | F23: заседание ВЕЭС | G23: онлайн | H23: В.Путин: Уважаемые друзья, коллеги! Я, так же как и вы, хотел бы выразить удовлетворение тем, что, несмотря на известные трудности, связанные с пандемией коронавируса, наше интеграционное взаимодействие продолжается и продолжает углубляться. И выступления коллег подтверждают, что мы все заинтересованы в дальнейшем поступательном развитии Евразийского экономического союза, тесно сотрудничаем и добиваемся результатов, причём в самых разных областях, прежде всего в экономике и торговле. Успешно реализуется такой важный совместный проект, как «Стратегические направления развития экономической интеграции до 2025 года», который мы с вами утвердили в конце прошлого года. Практически во всех государствах Евразэс возобновился экономический рост. В частности, в России по итогам первых шести месяцев 2021 года ВВП увеличился на 4,8 процента. При этом во всём Евразийском союзе повысились промышленное производство – на 4,4 процента и выпуск сельхозпродукции – на 0,6 процента. Хорошие темпы набраны во взаимной торговле: в январе – июне товарооборот между государствами – членами Евразэс увеличился почти на треть (31,9 процента), а объём внешней торговли Евразийского союза с третьими странами – на четверть. Причём таких показателей удалось добиться несмотря на то, что некоторые государства – члены Евразэс подвергаются – мы знаем об этом и говорили об этом – нелегитимным санкциям со стороны некоторых стран. Ни для кого не секрет, что эти санкции используются не только как инструмент недобросовестной конкуренции, но и как средство для подрыва законных правительств путём создания социальных, экономических и политических проблем или усугубления имеющихся проблем, которых достаточно в любой стране. Такие внешние неблагоприятные условия, как нам представляется, должны дополнительно стимулировать укрепление сотрудничества внутри нашего союза. Повышается значимость самого тесного взаимодействия в целях перехода на национальные валюты и сокращения использования доллара и евро во взаимных расчётах, организации импортозамещения, развития передовых высокотехнологичных отраслей, обеспечения населения необходимым продовольствием. Кстати, в России накоплен большой опыт развития в условиях западных ограничений, и мы готовы им делиться с партнёрами по Евразэс. Сообща проще и быстрее реализовывать крупные экономические проекты. Не могу не согласиться с нашим председателем [Касым-Жомартом Токаевым], что наблюдается дефицит этих проектов, их нужно, конечно, искать и внедрять, внедрять новые технологии, удовлетворять растущий спрос на качественные товары и услуги со стороны потребителей и тем самым эффективно противостоять любому внешнему давлению. В этом контексте считаем важным продолжать в Евразэс планомерную работу по наращиванию кооперации в промышленной и сельхозсферах, обеспечению максимальной свободы движения товаров, услуг, капитала и рабочей силы – так, чтобы сформировать действительно полноценный, устойчивый общий рынок. Подчеркну, что по всем этим направлениям уже многого удалось добиться. За последнее время государства – члены Евразэс существенно продвинулись в унификации регулирования розничной торговли товарами. Начат процесс гармонизации национального регулирования в сфере защиты прав потребителей, одобрены общие принципы и подходы к обеспечению продовольственной безопасности. Сегодня на наше утверждение представлено решение о переходе ко второму этапу формирования общих рынков нефти и нефтепродуктов Евразийского экономического союза. Подготовлен и проект совместного заявления о сотрудничестве в экологической сфере. Этот документ отражает понимание того принципиального значения, которое имеет борьба с изменением климата и сохранение окружающей среды для всех наших государств. На повестке дня – интенсификация взаимодействия по природоохранной тематике и, в частности, выработка гармонизированной системы климатического регулирования, с тем чтобы компании наших стран работали по понятным и согласованным правилам, касающимся экологии и защиты окружающей среды. Отмечу, что в России в настоящее время предпринимаются активные усилия по снижению углеродоёмкости экономики, сокращению эмиссии парниковых газов, развитию «зелёной энергетики». И мы предлагаем в рамках Евразэс начать унификацию стандартов по вопросам углеродной отчётности, осуществлять взаимовыгодные климатические проекты, совместно создавать собственные технологии, основанные на использовании безуглеродных источников энергии, конечно, включая и такие, как атомная и гидроэнергетика. Ещё одно направление взаимодействия государств Евразийского союза, которому следовало бы уделять особое внимание, на наш взгляд, это цифровизация. Об этом мы сегодня тоже говорим. Работа в данной сфере набирает обороты, что, безусловно, отвечает интересам как деловых кругов, так и граждан наших стран, поскольку упрощает ведение бизнеса, повышает мобильность и доступность услуг. В качестве примера приведу запуск 1 июля совместного цифрового проекта на евразийском пространстве – унифицированной системы поиска «Работа без границ». Этот электронный сервис предоставляет доступ к информации о вакансиях, анкетам соискателей по всему Евразийскому союзу. Цифровые технологии во многом помогают адаптировать экономики наших стран, да и вообще нашу жизнь, к ситуации, вызванной распространением коронавирусной инфекции. Разработанное в России мобильное приложение «Путешествую без COVID-19» стало существенным подспорьем в восстановлении свободы передвижения граждан по территории государств – членов Евразэс. Оно надёжное и удобное, люди оценили его эффективность, поэтому в число участников данного проекта вошли также и наши соседи: Азербайджан, Молдавия, Таджикистан и Узбекистан. Уважаемые коллеги! Не могу не отметить, что развивающаяся интеграция в рамках Евразэс привлекает заинтересованное внимание целого ряда зарубежных стран, вы об этом уже говорили. Важно, что к работе Евразийского союза всё активнее подключаются государства-наблюдатели. Они имеют возможность участвовать в деятельности интеграционных органов, причём на всех уровнях, знакомиться с процессом подготовки интеграционных документов и исполнения принятых решений. Эффективно реализуется на практике гибкая система связей Евразэс и с другими государствами, а также интеграционными структурами, такими как ШОС и АСЕАН. В июле вступило в силу соглашение о свободной торговле с Сербией, ведётся обсуждение аналогичных договоров с Египтом, Ираном, одобрен запуск переговоров с Индией. В активной фазе – работа исследовательских групп по изучению целесообразности создания зон свободной торговли с Индонезией и Монголией. Всё это очень полезно с точки зрения возможного расширения евразийской интеграции и воплощения в жизнь инициативы создания Большого Евразийского партнёрства. Вообще, подчеркну, что чем более очевидными будут реальные достижения Евразэс в экономике, торговле, социальной сфере, а главное – в деле повышения благосостояния граждан, тем, конечно, весомее будет авторитет нашего объединения, его влияние в мире. Это очевидные вещи. В заключение хотел бы выразить признательность казахстанским партнёрам, которые, председательствуя в Евразэс в текущем году, в столь непростой обстановке всемерно способствуют дальнейшему развитию интеграционных процессов. Благодарю вас за внимание. | I23: http://www.kremlin.ru/events/president/transcripts/deliberations/66927 | J23: 22 | K23: 0 | L23: 9 | M23: 1 | N23: 0 | O23: 7 | P23: 1
A24: Россия | B24: 2021 | C24: 21 мая | E24: Путин | F24: заседание ВЕЭС | G24: онлайн | H24: Уважаемые друзья, коллеги! Я всех приветствую. Но особенно хотел бы поблагодарить Президента Кубы товарища Мигеля Диас-Канеля Бермудеса прежде всего потому, что он счёл возможным присоединиться к нашей сегодняшней онлайн-встрече, несмотря на то что в Гаване только пять утра. Разговор об актуальных задачах развития евразийской интеграции действительно назрел, и я благодарю казахстанских наших друзей за то, что они организовали такую встречу. Накопилось действительно много вопросов, по которым нужно принять решения, причём решения уже нужно принимать и на нашем уровне, чтобы они были окончательно затверждены. Вполне естественно, что в наших дискуссиях ключевое, приоритетное место занимает тематика взаимодействия в борьбе с пандемией коронавируса, в преодолении её социально-экономических последствий. Что касается России, то, вы знаете, нам удалось достаточно быстро создать три собственные весьма эффективные и безопасные вакцины от коронавируса. Скоро будет запущена в оборот четвёртая вакцина – «Спутник Лайт». Наши соответствующие службы занимаются вакцинацией российских граждан, и достаточно активно идёт эта работа. Выпуск «Спутника V» успешно локализован – здесь коллеги уже говорили – и в Казахстане, и в Белоруссии. Россия – единственная страна, которая передаёт технологии по вакцинам. Рассматривается теперь возможность развёртывания таких производств в Армении и Киргизии. С учётом нынешних обстоятельств считаем важным уделить особое внимание сотрудничеству в области лекарственной безопасности. Кстати говоря, у нас и лекарственные препараты появились отечественные, весьма эффективные в борьбе коронавирусом. До конца года эксперты Евразэс должны подготовить план мероприятий по обеспечению наших стран стратегически значимыми лекарственными препаратами для лечения не только коронавируса, но и других опасных заболеваний. По сути, речь идёт о том, чтобы уже в ближайшей перспективе организовать производство эффективных и доступных лекарств в Евразэс в объёмах, достаточных для удовлетворения потребностей наших национальных систем здравоохранения. Также хочу выделить совместный проект по созданию цифровой платформы «Путешествую без COVID-19», реализуемый при содействии Фонда цифровых инициатив Евразийского банка развития. По-моему, наши армянские коллеги и выступали с этой инициативой. Цель проекта – облегчение взаимных поездок граждан наших стран, существенное ускорение процедур пересечения государственных границ при соблюдении санитарных норм и с учётом текущей эпидемиологической ситуации. Я разделяю озабоченности Александра Григорьевича Лукашенко, когда он говорит о сегодняшних ограничениях. Но со своей стороны Россия стремится и будет стремиться максимально улучшить условия для прибывающих к нам на работу граждан зарубежных стран, и конечно, в первую очередь из государств – членов Евразэс. В ближайшее время нами будут запущены унифицированная интернет-система «Работа без границ» и соответствующее мобильное приложение, которые позволят в онлайн-режиме оформлять все документы, требующиеся для трудоустройства. И конечно, на наш взгляд, необходимо наращивать усилия стран Евразэс по координации политики в сфере экономического развития и решения насущных социальных проблем, в том числе вызванных пандемией. Механизмы интеграции должны работать максимально эффективно, способствовать росту взаимных торговых и инвестиционных связей, промышленной кооперации. Только так мы сможем добиться улучшения макроэкономических показателей, а тем самым и повышения уровня жизни наших граждан. Подчеркну, мы поддерживаем подготовленные к утверждению на нашей сегодняшней встрече основные ориентиры макроэкономической политики государств – членов Евразэс на 2021–2022 гг. Как представляется, этот документ весьма содержательный, и реализация предложенных в нём мер будет способствовать не только стабилизации экономик наших стран, но и их выводу на траекторию роста. Безусловно, внимания требуют вопросы укрепления единого общего рынка – коллеги здесь уже говорили об этом, – устранения ненужных барьеров и ограничений на пути торговли товарами и услугами. Работа на этом участке ведётся последовательно, целенаправленно. В результате, даже несмотря на вызванные пандемией трудности, товарооборот между государствами – членами Евразэс в январе–марте текущего года увеличился на 17 процентов. Сейчас на фоне нестабильной мировой конъюнктуры обостряются проблемы, связанные с резким колебанием цен на социально значимые продукты, – выступавшие коллеги тоже уже об этом сказали. Признательны партнёрам за поддержку российской инициативы по нормализации ситуации в этой сфере. У нас конкретные есть решения по этому вопросу. В частности, не так давно Евразийская комиссия приняла конкретные решения, направленные на консолидацию ценовой политики государств Евразэс на рынке сахара. Столь же оперативно следует принимать меры и по другим видам продукции, когда это потребуется. Стоило бы также активизировать совместную работу по проблематике борьбы с изменением климата и охраны окружающей среды. Как известно, международные усилия на экологическом направлении становятся драйвером глобальной технологической трансформации. Мы видим, что все страны Евразэс проявляют большой интерес к тому, чтобы разрабатывать и внедрять «зелёные» технологии, реализовывать собственные инновационные проекты в этой сфере. Но, конечно, нельзя допустить, чтобы эта тема использовалась как ещё один инструмент каких-то ограничений в экономике. Поэтому предлагаем подумать над тем, чтобы сформировать в союзе банк климатических данных и цифровых инициатив, в том числе касающихся учёта углеродного следа. Пользоваться этим банком мы могли бы все – все компании наших стран, работающие над проектами, нацеленными на улучшение экологической обстановки. Уважаемые коллеги! Мы с удовлетворением отмечаем, что развивающиеся интеграционные процессы в рамках Евразэс привлекают внимание целого ряда зарубежных государств, вы сегодня тоже об этом сказали. Последовательно расширяются и диверсифицируются внешние связи нашего объединения. Разработана и успешно применяется гибкая система взаимодействия с государствами, интеграционными структурами и международными организациями. Эта система позволяет поддерживать и развивать торгово-экономические связи с партнёрами на разных курсах и уровнях, учитывая при этом их настрой и их готовность к выстраиванию интеграционного сотрудничества на основе взаимной выгоды и уважения друг друга. Мы выступаем за дальнейшее увеличение числа преференциальных договоров с крупнейшими нашими торговыми партнёрами союза. Напомню, такие документы уже подписаны между Евразэс и Вьетнамом, Сербией, Ираном, Сингапуром. Считаем важным активизировать переговоры по аналогичным документам с Израилем и, как Александр Григорьевич предложил, с Египтом – мы тоже это поддерживаем. Скорее начать переговорный процесс с нашим крупным партнёром – Индией, внимательно изучить вопрос о целесообразности заключения соглашений о свободной торговле с другой большой страной – Индонезией, с нашим соседом Монголией. Мы с вами неоднократно говорили о сопряжении интеграционных процессов Евразэс с реализуемой Китаем инициативой «Один пояс, один путь». Согласен с коллегами: шагом к этому стало заключение Соглашения о торгово-экономическом сотрудничестве между Евразийским союзом и КНР. Нужно, конечно, двигаться дальше. Но уже этот документ последовательно выполняется, тем самым создаётся хорошая основа для практического осуществления выдвинутой идеи формирования большого евразийского партнёрства в сфере безопасности, экономической и гуманитарной областях. В целом мы удовлетворены тем, как развивается взаимодействие в Евразэс. Главное, что оно приносит реальные экономические выгоды, которые ощущает население наших стран. Я упомянул о том, что, несмотря на все трудности, всё-таки торговля подрастает, и это очень хороший признак того, что мы всё-таки в правильном направлении действуем и наши усилия приносят конкретный результат. Благодарю вас за внимание. | I24: https://barnaul.mid.ru/ru/press-centre/news/vystuplenie_prezidenta_rossiyskoy_federatsii_v_v_putina_v_rezhime_videokonferentsii_na_zasedanii_vys/ | J24: 17 | K24: 0 | L24: 4 | M24: 0 | N24: 0 | O24: 12 | P24: 1
A25: Россия | B25: 2022 | C25: 9 декабря | D25: в расширенном составе | E25: Путин | F25: заседание ВЕЭС | G25: Бишкек | H25: В.Путин: Я прежде всего хотел бы присоединиться к словам благодарности в адрес Президента Кыргызстана и поблагодарить всех наших киргизских друзей за работу, которая была проделана в качестве председателя Евразийского экономического союза. В этом году наше интеграционное объединение работало эффективно, продолжало последовательно развиваться. В условиях волатильности глобальных рынков и неблагоприятной мировой политической конъюнктуры по линии Евразэс были предприняты своевременные и эффективные [шаги], позволяющие не только стабилизировать макроэкономическую ситуацию в наших странах, но и добиться улучшения целого ряда показателей развития, стимулировать рост ключевых отраслей экономики, а также оказать поддержку сложившимся на пространстве союза хозяйственным связям. В частности, уровень безработицы за девять месяцев 2022 года сократился, и сократился в государствах Евразэс очень прилично, очень заметно – на 18 процентов, – и составляет чуть более одного процента, 1,1 процента, от общей численности рабочей силы. Я обращаю внимание коллег, что уровень безработицы является одним из ключевых показателей состояния экономики в целом. К слову, в Евросоюзе безработица – семь процентов, то есть в семь раз больше, чем у нас. Увеличилось производство продукции сельского хозяйства на 5,4 процента – это очень заметный и очень хороший рост. Это тем более важно – здесь коллеги уже говорили, Александр Григорьевич [Лукашенко] об этом упоминал – на фоне, к сожалению, растущего продовольственного кризиса в мире. Никол Воваевич [Пашинян] тоже обратил внимание на то, что мы согласовали индикативные балансы, то есть мы абсолютно выровняли все наши потребности. Рост на 5,4 процента в сегодняшних условиях – это очень хороший показатель. Растут объёмы выполненных строительных работ, причём на 4,7 процента. Тоже очень хороший показатель, имея в виду, что стройка тянет за собой очень много других производств. Совокупный прирост инвестиций в основной капитал достиг 6,6 процента – тоже очень хорошо. Должен сказать, что мы удерживаем в рамках разумного, на очень хорошем уровне и другие макроэкономические показатели, в том числе инфляционные. Касым-Жомарт Кемелевич [Токаев] говорил о том, что в мире инфляционные процессы растут, это раскачивает мировую экономику. Мы этот параметр в целом держим под контролем. У нас – для примера – в России в этом году дефицит бюджета будет два процента, в следующем году мы планируем тоже два, в 2024-м – уже 1,4, в 2025-м уже будет 0,7. Я уверен, что мы это сделаем. Что касается инфляции, то в этом году он [показатель] будет для нашей экономики приемлемым – 12,2 [процента], в следующем мы рассчитываем – по итогам следующего квартала [2023 года] – уже к пяти процентам подойти, а может быть, и ниже. У нас очевидный тренд на снижение инфляции. Это для всех наших стран имеет значение, потому что макроэкономические показатели в российской экономике так или иначе влияют на экономики всех наших стран. Мы знаем, что в странах Еврозоны самые большие показатели по инфляции за последние 30–40 лет – все двузначного значения, а в некоторых странах Евросоюза достигают заоблачных величин для европейской экономики – 20 и более процентов. Кстати говоря, что касается развития экономики в целом, нам предрекали спад экономики под 20 процентов – спад будет в этом году 2,9 процента. В следующем мы ожидаем 0,9 и будем дальше двигаться в позитивном тренде. Обеспечена бесперебойная торговля всеми жизненно необходимыми товарами в рамках Евразэс, кстати говоря, включая – по продовольствию я уже сказал – и энергетику. В этой связи, конечно, не могу не отметить, что тарифы, цены на энергоносители в странах Евразэс кардинально отличаются от соответствующих тарифов у наших соседей на Западе. Скажем, разница в ценах на газ в странах Евразэс и Евросоюза в десять и более раз – не в какие-то проценты, а в десять и более раз. Это, конечно, создаёт соответствующие условия для экономического развития в нашей зоне. В текущем году в Евразэс принят ряд принципиальных решений, направленных на снятие остающихся таможенных и административных барьеров. Я не могу не согласиться с Александром Григорьевичем, когда он говорит о том, что нам нужно эффективнее работать по устранению этих барьеров, это правда. Они мешают свободной торговле между нашими странами, и мы должны над этим энергичнее работать. Между тем ускорилась работа по переходу на национальные валюты во взаимных расчётах. Здесь тоже Александр Григорьевич прав. Начат процесс создания общей платёжной инфраструктуры и интеграции национальных систем передачи финансовой информации. Государства «пятёрки» тесно взаимодействуют в сфере транспорта и логистики, растут объёмы взаимных грузоперевозок, чему во многом помогло дополнительное обустройство и увеличение пропускной способности пограничных переходов между нашими странами. Хотя и здесь, конечно, нужно ещё поработать и есть над чем работать. В рамках Евразэс сейчас реализуется целый ряд интеграционных инфраструктурных проектов, нацеленных на создание и эффективное использование магистральных международных коридоров «Восток – Запад» и «Север – Юг». И тоже хочу отметить: очень много заинтересованных стран проявляют себя и хотят присоединиться к этим проектам, в том числе и совместно с нами инвестировать в эту работу. Отмечу, что государства – участники союза продолжают успешно развивать взаимовыгодную промышленную кооперацию. Сегодня мы принимаем решение об учреждении в Евразэс нового специализированного механизма финансирования промышленности. Такой механизм позволит кредитовать и субсидировать перспективные совместные проекты, в том числе связанные с организацией импортозамещающих производств. Всё более активно продвигается сотрудничество и в сфере энергетики. По итогам нынешнего заседания будет принято решение об учреждении совета руководителей уполномоченных органов государств Евразэс в сфере энергетики. Мы сегодня в закрытом составе достаточно откровенно и предметно говорили, по-моему, взаимное понимание есть, обязательно будем двигаться по выполнению всех наших планов. Россия, конечно, поддерживает создание такой координационной структуры, о которой я только что сказал, которая профессионально займётся вопросами, связанными с обеспечением национальных экономик на долгосрочной основе ключевыми энергоресурсами и формированием общих энергетических рынков союза. У нас есть планы соответствующие, и мы будем стремиться к их выполнению. Уважаемые коллеги! В следующем году председательство, как вы уже отмечали, в Евразийском экономическом союзе переходит к Российской Федерации. Позвольте мне в общих чертах хотя бы изложить намечаемые нами приоритеты в работе. В первую очередь полагаем необходимым актуализировать стратегические ориентиры развития Евразэс. Действующий базовый документ «Направления развития экономической интеграции» рассчитан на период до 2025 года, и важно приступить к подготовке новых документов стратегического планирования, задающих основные векторы дальнейшего интеграционного взаимодействия на среднюю и долгосрочную перспективу. В качестве одного из таких векторов рассматриваем укрепление технологического суверенитета государств – членов Евразэс и формирование нашими странами общей инновационной и промышленной базы в ключевых индустриальных и сельскохозяйственных отраслях. Мы в закрытом режиме обсуждали этот вопрос, тоже хочу обратить внимание на то, что было сказано Президентом Белоруссии. У нас в принципе кооперация развивается неплохо, в последнее время наметилась работа такая позитивная по некоторым ключевым важнейшим направлениям взаимодействия. Уверен, что это приобретёт более широкий характер в целом в нашей организации. Целесообразно продолжать и усилия по совместному внедрению информационных технологий, в том числе в области электронного документооборота, автоматического обмена транспортной и таможенной информацией между ведомствами и перевозчиками государств союза, а также в сфере маркировки и прослеживаемости товаров, где цифровые решения уже помогают пресекать обращение на союзном рынке небезопасной и некачественной продукции. Также предлагаем сосредоточить работу «пятёрки» на наращивании инвестиционного сотрудничества, создании благоприятных условий для взаимных капиталовложений, упрощении соответствующих административных процедур и повышении гарантий защиты прав инвесторов. Неотъемлемым элементом такой работы считаем гармонизацию режимов налогового регулирования в государствах Евразэс и в этих целях синхронное внедрение передовых механизмов налогового контроля. И конечно, в ходе председательства намерены заниматься вопросами, связанными с развитием научных, технических и образовательных контактов. Предлагаем коллегам подумать над новыми идеями и инициативами в целях поощрения практики межвузовского сотрудничества, совершенствования программ стажировок и академических обменов. Считаем полезным шире вовлекать молодых специалистов в интеграционную повестку через программы студенческого туризма, популяризацию общих исторических, социальных и этических ценностей, в поддержку совместных молодёжных проектов в сферах предпринимательства, добровольчества, культуры и спорта. Как вы все не раз подчёркивали, Евразийский экономический союз и в целом наша интеграционная работа привлекает внимание всё большего числа международных игроков, заинтересованность в развитии связей с нашим объединением проявляют многие иностранные государства. Я сейчас не буду всё повторять, я полностью согласен с предложениями коллег по расширению этой работы, в том числе и с региональными структурами, такими как ШОС и АСЕАН. Россия приветствует активизацию международных деловых связей и контактов Евразийского экономического союза и будет способствовать дальнейшему расширению спектра преференциальных и непреференциальных соглашений с зарубежными партнёрами. В заключение хотел бы выразить уверенность в том, что и в следующем году государства – участники Евразэс продолжат взаимодействие столь же тесно и конструктивно, как и в ходе киргизского председательства. Будем рады видеть вас на очередном заседании Высшего Евразийского экономического совета и на Евразийском экономическом форуме, который планируем провести 24–25 мая 2023 года. Как и договорились в узком составе, место нашей совместной работы, встречи мы определим в рабочем порядке. Конечно, вне рамок нашей сегодняшней работы хочу вам напомнить, что мы вас ждём на согласованной предновогодней неформальной встрече лидеров СНГ в Санкт-Петербурге. Благодарю за внимание. | I25: http://www.kremlin.ru/events/president/news/70058 | J25: 19 | K25: 0 | L25: 6 | M25: 2 | N25: 0 | O25: 14 | P25: 0
A26: Россия | B26: 2022 | C26: 27 мая | E26: Путин | F26: заседание ВЕЭС | G26: Бишкек | H26: В.Путин: Уважаемые коллеги, добрый день! Поддерживаю тех, кто выступал и позитивную оценку давал деятельности Евразийского экономического союза. Действительно, в рамках Евразэс наращиваются темпы интеграционного строительства, повышается эффективность общих рынков товаров, услуг, капиталов, рабочей силы. Шаг за шагом формируется всеобъемлющее единое экономическое пространство Евразэс. Как уже отмечалось, 29 мая исполнится восемь лет со дня подписания основополагающего Договора о Евразэс. За это время мы прошли по-настоящему большой путь, развивая сотрудничество на принципах равноправного диалога и взаимного уважения, укрепляли и значительно укрепили наш Евразийский союз. Сделали это действительно эффективно, превратили его в эффективный и влиятельный региональный экономический организм, организацию. Налицо значительные достижения по ключевым направлениям сотрудничества: в торговле, промышленности, финансах и сельском хозяйстве. И, что самое главное, пользу от интеграционной работы, которой мы последовательно занимаемся, на практике, в своей повседневной жизни ощущают граждане наших стран. И мы полностью поддерживаем подготовленное решение объявить 29 мая Днём Евразийского союза. Таким образом, в календаре появится новая знаменательная дата, объединяющая наши народы и символизирующая общую приверженность государств Евразэс интеграционному строительству. Тот факт, что евразийская интеграция приносит реальную отдачу, подтверждают конкретные экономические показатели. Устойчивыми темпами растёт взаимная торговля между государствами – членами Союза. По итогам 2021 года объём товарооборота, по нашим данным, по данным нашей статистики, прибавил порядка трети и составил 72,6 миллиарда долларов. При этом совокупный валовый внутренний продукт стран Евразэс вырос на 4,6 процента (в России он чуть больше – на 4,7 процента). Прирост промышленного производства составил 5,3 процента, инвестиций в основной капитал – 6,8 процента, объёма выполненных строительных работ – 5,4 процента, ввода в эксплуатацию жилья – 12 процентов, грузооборот вырос на 4,7 процента. Важно, что наша совместная работа строится в плановом порядке и на системной основе. Последовательно осуществляется программа стратегического развития евразийской экономической интеграции до 2025 года. Экономические ведомства и регуляторные органы наших стран продолжают усилия по выявлению и ликвидации остающихся ограничений и барьеров на пути свободного движения товаров, услуг, капитала и рабочей силы на внутреннем рынке Евразэс. Только за два последних года снято 30 подобного рода ограничений. И конечно, сама жизнь диктует необходимость создания действительно безбарьерного, единого рынка на пространстве Евразэс. Мы все убеждены, что более тесная интеграция позволит нашим странам стать экономически сильнее и значительно уменьшить зависимость от внешней, в том числе и политической, конъюнктуры. Преимущества интеграционного курса особенно очевидны сейчас, в нынешней непростой международной обстановке, в условиях практически агрессии со стороны некоторых недружественных нам государств. Здесь Президент Белоруссии говорил об этом конкретно. Но мы хотели бы отметить, что Правительством России принимаются своевременные решения для стабильного, уверенного функционирования рынков и финансового сектора. Большое внимание оказывается поддержке ключевых отраслей и системообразующих предприятий. Значительно упрощён порядок ведения бизнеса – значительно снижена административная нагрузка, чтобы максимально обеспечить свободу предпринимательства. Работаем также над повышением доступности финансирования для пополнения оборотных средств, поддержания банковской ликвидности. В этих целях расширяем практику расчётов в национальных валютах в торговле с теми странами, которые на деле доказали, что являются надёжными партнёрами России. К слову, доля платежей в нацвалютах во взаимных расчётах стран Евразэс уже достигла 75 процентов. Отмечу в этой связи, что по инициативе России евразийской «пятёркой» принят целый ряд срочных антикризисных мер, направленных на минимизацию последствий санкций, на повышение устойчивости наших экономик, укрепление макроэкономической стабильности, помощь предпринимателям и гражданам наших государств. Так, Евразийской экономической комиссией уже утверждено более 30 антикризисных решений, и это, безусловно, даёт свой эффект. В сфере таможенного регулирования начиная с марта одобрено три пакета мер по обнулению пошлин на более чем 1600 товарных позиций критического импорта. В результате экономия импортёров за следующие полгода может составить порядка 800 миллионов долларов. Кроме того, скорректированы требования технических регламентов Союза. Для сдерживания цен Комиссия подняла пороги беспошлинного ввоза товаров для личного пользования до тысячи евро. Реализуются шаги по импортозамещению и дальнейшему углублению промышленной кооперации стран Союза в стратегических отраслях, включая гражданское авиастроение и фармацевтику. Готовится межгосударственная программа по расширению электронной вычислительной инфраструктуры стран Евразэс. Продолжается деятельность по цифровизации логистических коридоров, внедрению высокотехнологичных сервисов таможенного администрирования, развитию и повышению качества интернет-торговли. Полагаю важным и далее уделять особое внимание вопросам обеспечения продовольственной безопасности. Вы знаете, что в мире складывается ситуация непросто. Наши страны вносят очень серьёзный вклад в решение этих проблем, и Россия, и все другие члены нашей организации ведут себя в высшей степени ответственно. На сегодняшний день наши пять стран за счёт собственного производства полностью покрывают внутренние потребности по ключевым видам продовольствия и сельхозтоваров. Учитывая, что Евразэс – это и крупнейший в мире экспортёр сельхозпродукции, как я уже сказал, в нашей организации предпринимаются все возможные меры, в том числе таможенно-тарифного и нетарифного регулирования, для обеспечения устойчивости цепочек поставок. Уважаемые коллеги! Вызывает удовлетворение, что, даже несмотря на сложную международную ситуацию, на развязанную так называемым коллективным Западом конфронтацию, на то, что наши недоброжелатели пытаются чинить всяческие препятствия нашей интеграции, всё-таки – и коллеги сейчас об этом говорили – совершенно очевидно для нас всех, что растёт интерес к деятельности Евразийского экономического союза со стороны многих зарубежных партнёров. В настоящее время – здесь уже перечислялись эти страны – активно ведутся переговоры по заключению полноформатного соглашения о свободной торговле, в том числе и с Ираном. Это соглашение призвано заменить действующее временное соглашение от 2018 года, реализация которого уже заметно сказалась на товарообороте Союза с Исламской Республикой: по итогам 2021 года товарооборот вырос на 73,5 процента – до пяти миллиардов долларов, экспорт из Евразэс увеличился в 2,1 раза – до 3,4 миллиарда долларов. Чтобы сохранить нынешний преференциальный режим торговли с Ираном до заключения нового соглашения о свободной торговле, мы поддерживаем решение продлить временное соглашение. Полагаем также целесообразным активизировать переговоры по соглашению о свободной торговле с Египтом, начать аналогичные переговоры с Индонезией и, кроме того, изучить вопрос о заключении преференциального торгового соглашения с Объединёнными Арабскими Эмиратами. В заключение присоединяюсь к уже прозвучавшим словам благодарности в адрес Президента Киргизии Садыра Нургожоевича Жапарова за организацию нашей работы. Мы отмечаем те усилия, которые Киргизия прикладывает в качестве председателя в Евразийском экономическом союзе для обеспечения эффективной деятельности нашего объединения в нынешнем году, и стремимся оказывать киргизским друзьям всяческое содействие и будем так поступать в будущем. Хочу вновь подчеркнуть: для России углубление союзнических связей со всеми государствами Евразэс – ключевой приоритет. Очень надеемся, что и наши ближайшие партнёры, включая Узбекистан, изучая все преимущества сотрудничества в рамках организации, будут делать шаги в направлении, удовлетворяющем интересам самого Узбекистана, но и соответствующим образом развивая наше объединение. Мы со своей стороны – хочу подчеркнуть – будем делать всё для поддержки интеграционных процессов на пространстве Евразии. Благодарю вас за внимание. | I26: http://www.kremlin.ru/events/president/news/68494 | J26: 22 | K26: 1 | L26: 13 | M26: 0 | N26: 0 | O26: 18 | P26: 1
A27: Россия | B27: 2023 | C27: 24-25 мая | D27: в расширенном составе | E27: Путин | F27: заседание ВЕЭС | G27: Москва | H27: В.Путин: Дорогие друзья, коллеги! Мы начинаем нашу работу в широком составе, как и договорились. Я, с вашего позволения, начну наши публичные выступления и потом предоставлю слово всем присутствующим. Подведём затем итог нашей дискуссии и перейдём к документам. Только что мы завершили заседание Высшего Евразийского экономического совета в узком составе: обменялись мнениями по важным аспектам деятельности нашего объединения, наметили стратегические перспективы углубления интеграционного сотрудничества. И теперь, как я уже сказал, продолжим работу с участием делегаций. Мне приятно отметить, что в сегодняшнем заседании в качестве гостя впервые принимает участие Президент Азербайджанской Республики Ильхам Гейдарович Алиев. Хотел бы поприветствовать его и всю азербайджанскую делегацию, присоединившегося к нам по видеосвязи главу государства – наблюдателя при Евразэс, Президента Узбекистана Шавката Миромоновича Мирзиёева – он на наших экранах, Шавкат Миромонович, приветствуем Вас – и Президента Таджикистана Эмомали Шариповича Рахмона – Эмомали Шарипович, привет, Вы нас видите, слышите. Спасибо, что вы сегодня вместе с нами. Хочу выразить уверенность, что ваши страны будут наращивать продуктивное и многоплановое сотрудничество с «пятёркой». Символично, что наша встреча проходит в канун празднования Дня Евразийского экономического союза (29 мая), учреждённого решением Высшего совета в прошлом году и знаменующего общую приверженность государств Евразэс дальнейшему развитию интеграции. С удовлетворением отмечаю, что сотрудничество в рамках Евразийского союза продолжает укрепляться и наше объединение последовательно утверждается в качестве одного из самостоятельных и самодостаточных центров формирующегося многополярного мира. При этом взаимодействие стран «пятёрки» неизменно выстраивается на принципах взаимной выгоды, учёта интересов друг друга и с ориентиром на обеспечение устойчивого экономического роста и улучшение благосостояния жителей всех наших государств. Именно на достижение этих ключевых целей направлены мероприятия, проводимые российским председательством в организациях Евразэс в текущем году. При этом мы совместно будем стремиться к тому, чтобы в рамках нашего объединения был достигнут одинаково высокий уровень развития. Ну, за Арменией нам сложно будет угнаться, сегодня мы это уже констатировали, у них рост ВВП составляет 12 с лишним процентов. Это очень высокий, серьёзный показатель. Надо сделать так, чтобы граждане всех пяти стран, приезжая в другое государство Союза работать, учиться или вести бизнес, чувствовали себя комфортно, как дома. Добиваться этого можно, если поддерживать внутри Союза реальную, стопроцентную свободу передвижения товаров, услуг, финансов и человеческого капитала, обеспечивать сопряжение конкурентных преимуществ наших государств. Как раз на это ориентированы новые базовые документы стратегического планирования Евразэс, которые зададут основные векторы совместных действий на средне- и долгосрочную перспективу в горизонте до 2030 и 2045 годов. Работа над этими документами, охватывающими самый широкий спектр отраслей интеграции, уже ведётся, и мы предлагаем её активизировать, чтобы до конца года выйти на видимые, осязаемые результаты. И рассчитываю на то, что профильные ведомства наших стран будут действовать именно в таком ключе. Что касается конкретных задач дальнейшего взаимодействия в рамках Евразэс, то прежде всего хотел бы отметить необходимость развития промышленной кооперации, увеличения количества новых совместных производств под общей торговой маркой «Сделано в Евразэс». Важно, чтобы такой новый бренд как можно скорее стал узнаваемым и завоевал популярность потребителей во всех наших странах, а «Евразийский знак качества» на товарах, изготовляемых на территории государств «пятёрки», означал соответствие продукции самым высоким стандартам. Разумеется, востребованы слаженные усилия по укреплению технологического суверенитета в системообразующих секторах экономики, по достижению подлинной технологической самодостаточности. В практическом плане предложил бы согласовать и реализовать единые приоритеты технологической трансформации и инновационного сотрудничества, которые позволяли бы нашим странам не зависеть по критически значимым отраслям от иностранных технологий и компаний, тем более если мы встречаем определённые тенденции, связанные с ограничением сотрудничества со стороны других стран в этих отраслях. В этом же контексте можно было бы подумать над созданием евразийских технологических альянсов с подключением заинтересованных партнёров из третьих стран. Целью таких альянсов могла бы стать организация на территории наших государств новых наукоёмких высокотехнологичных производств. На повестке дня и обеспечение цифрового суверенитета Евразэс. Напомню, что процесс налаживания партнёрства «пятёрки» в IT-сфере Россия инициировала ещё в 2017 году. Важно, чтобы государства – члены союза сформировали единую цифровую экосистему, что подразумевало бы интеграцию национальных систем электронных государственных услуг и электронных правительств каждого из участников «пятёрки». Смею вас заверить, что Россия здесь продвинулась достаточно далеко и сделала очень хорошие заделы. И конечно, общие усилия должны быть направлены на упрочение финансового суверенитета Евразэс путём обеспечения устойчивой кредитно-банковской и расчётной инфраструктуры, развития и гармонизации евразийского финансового рынка. Тем самым будут созданы благоприятные условия для того, чтобы капиталы оставались в границах наших стран и инвестировались в дальнейшее укрепление экономик государств-членов. В этих целях было бы полезно учредить и евразийское рейтинговое агентство, которое обеспечило бы наличие адекватного оценочного инструментария для обслуживания растущей экономической активности на территории Евразии. Здесь, конечно, нужны принципиальные подходы, жёсткие критерии и умение подчиняться этим критериям – сделать так, чтобы эта работа была абсолютно объективной, в этом вся её ценность. Если этого не будет, то тогда в этом просто нет смысла. Упомяну и о том, что в этом году российским председательством уделяется значительное внимание вопросам, связанным с изменением климата. Синхронизацией подходов «пятёрки» в области климатического регулирования мог бы заняться Климатический и экологический клуб Евразэс, в задачи которого входила бы реализация совместных научных исследований и разработок, внедрение «зелёных» технологий, достижение международного признания евразийских климатических инициатив, улучшение состояния водных экосистем, сохранение биологического разнообразия, геологоразведка и освоение недр, осуществление проектов по переработке мусора и многое другое. Хотел бы также обозначить новое и, как представляется, многообещающее направление нашей работы: предложил бы добавить к известным четырём свободам (передвижения товаров, услуг, финансов и человеческого капитала в рамках Евразэс) пятую – свободу знаний, которая реализовывалась бы на основе общих принципов и стандартов образования, здравоохранения и государственного управления. Это будет способствовать формированию и развитию общего культурного пространства и, если позволите, общей евразийской идеологии. Мы сейчас только в узком составе достаточно подробно и неформально об этом говорили – о том, насколько это важно для всех нас. Это особенно важно для молодых людей, молодого поколения. Параллельно следовало бы активнее вести деятельность по популяризации нашего объединения, его достижений и возможностей для граждан государств-членов, гарантировать людям широкий доступ к достоверной информации об идущих интеграционных процессах, а также всемерно содействовать развитию туризма в рамках евразийского интеграционного контура, создавать сети новых туристических маршрутов. Естественно, нашей общей поддержки требует практика подготовки квалифицированных кадров и открытия новых рабочих мест в наиболее востребованных областях экономики. В этой связи необходимо стремиться к координации национальных образовательных и научных программ, гармонизации требований к профессиям, выработке общих учебных и профессиональных стандартов, запуску совместных образовательных курсов и единых учебников по техническим и другим дисциплинам. Следует также развивать межвузовское сотрудничество, программы стажировок и академических обменов. При этом сведения о таких возможностях должны быть доступны учащимся из всех стран Евразэс. Хочу отметить, что дальнейшее интеграционное строительство диктует необходимость укрепления, развития и модернизации созданных нами наднациональных инструментов и институтов, в первую очередь Экономической комиссии, которая должна быстро и адекватно реагировать на происходящие в мире изменения и принимать профессиональные решения, нацеленные на защиту наших общих интересов и продвижение взаимовыгодной интеграции. Можно было бы подумать о том, чтобы наделить Комиссию дополнительными полномочиями, но так, чтобы принцип консенсуса, заложенный в основу принятия всех ключевых решений в рамках Евразэс, оставался базовым, обеспечивая должное уважение к суверенитету каждой из стран – участниц Союза и делая его ещё более привлекательным для наших потенциальных партнёров и участников. И конечно, Евразэс должен активно развивать отношения со странами, которые стремятся к равноправному, взаимовыгодному партнёрству, я имею в виду наших партнёров в Азии, в Арабском мире, в Африке, в Латинской Америке, имею в виду сотрудничество с многосторонними объединениями, такими как Содружество Независимых Государств, Шанхайская организация сотрудничества, БРИКС и некоторые другие. Важно продолжать формирование зон свободной торговли с заинтересованными странами, и в том числе предложить им совместно использовать имеющуюся у участников «пятёрки» международную платёжную инфраструктуру в национальных валютах и цифровых валютах центральных банков. В заключение хотел бы ещё раз поблагодарить всех руководителей стран – членов Евразэс за тесное взаимодействие и взаимную поддержку при решении стоящих перед объединением задач. Хотел бы ещё раз поблагодарить всех, кто присоединился к нам, к нашей работе сегодня, не будучи членом нашей организации – пока. Уверен: действуя и далее сообща и слаженно, мы будем добиваться, обязательно добьёмся новых весомых результатов в развитии интеграционного сотрудничества в интересах наших государств и народов. Благодарю вас за внимание. И, как у нас принято, по алфавиту – передаю слово Премьер-министру Армении господину Пашиняну Николу Воваевичу. | I27: http://www.kremlin.ru/events/president/news/71204 | J27: 25 | K27: 0 | L27: 5 | M27: 4 | N27: 0 | O27: 13 | P27: 1
A28: Россия | B28: 2023 | C28: 25 декабря | D28: в расширенном составе | E28: Путин | F28: заседание ВЕЭС | G28: Санкт-Петербург | H28: : Уважаемые коллеги, друзья, добрый день! Я рад всех приветствовать. У нас сейчас состоялась беседа в узком составе. А вначале хотел бы поприветствовать Министра промышленности, рудников и торговли Исламской Республики Иран господина Аббаса Алиабади. Я ещё скажу в своём выступлении, хочу отметить, что мы в узком составе отмечали, что сегодня подписано соглашение о сотрудничестве и зоне свободной торговли между Евразэс и Республикой Иран. Думаю, что это очень хороший шаг вперёд, сейчас ещё скажу об этом. Мы, как я уже сказал, только что завершили заседание Высшего Евразийского экономического совета в узком составе, обменялись мнениями по важным аспектам деятельности нашего объединения, наметили стратегические перспективы углубления интеграционного сотрудничества. В частности, обсуждался вопрос о принятии декларации о дальнейшем развитии экономических процессов в рамках Евразийского экономического союза до 2030 года и на период до 2045 года. Эта идея была поддержана, все члены Высшего совета согласились утвердить декларацию, и соответствующее решение мы формализуем по итогам нашего заседания. По сути, декларация – это новый документ программного характера, которым предусмотрены шаги по наращиванию совместных усилий в ключевых отраслях, а также определены дополнительные сферы взаимодействия. Наши министры экономического блока, эксперты и профильные специалисты хорошо поработали над согласованием текста декларации. Документ вобрал в себя видение всех пяти стран союза, того, как дальше должна развиваться евразийская интеграция, полностью отражает мнения и интересы каждого из участников Евразэс и представляется весьма добротным. На встрече в узком составе подведены основные итоги деятельности Евразийского союза в ходе российского председательства, которое завершится 31 декабря, и российская сторона, безусловно, благодарна всем партнёрам по объединению за конструктивную совместную работу, в том числе по реализации приоритетов нашего председательства. Взаимодействие в рамках союза продолжает развиваться динамично и успешно по всем ключевым направлениям интеграционного строительства, даже несмотря на известные трудности, связанные с непростой международной внешней ситуацией. С удовлетворением отмечаем, что в текущем году во всех странах – членах объединения фиксируется стабильный рост экономик. Так, у нас в России за первые три квартала ВВП прибавил три процента, а по итогам года ожидается 3,5 процента. Прирост валового продукта, причём весьма значительный, имеется и в других государствах Евразэс. Насколько я знаю, за девять месяцев он составит в Армении более девяти процентов, это очень хороший показатель; в Казахстане – почти пять, да, Касым-Жомарт Кемелевич? В Киргизии – более четырёх процентов, а в Белоруссии, так же как и в России, – 3,5. Промышленное производство в Евразэс увеличилось на 3,5 процента. Строительная отрасль выросла на 9,3 процента. Что немаловажно, количество безработных в целом по Евразийскому союзу сократилось на 14,2 процента, а в России безработица вообще находится на минимальном историческом уровне – менее трёх процентов, 2,9. По имеющимся данным, за девять месяцев текущего года торговля между пятью нашими странами выросла на 8,9 процента. При этом улучшается её структура, увеличиваются поставки готовой высокотехнологичной продукции с одновременным снижением сырьевой составляющей. Важно, что доля национальных валют во взаимных расчётах превысила 90 процентов. И этот показатель, без сомнения, будет расти и в дальнейшем с учётом принимаемых нашими странами совместных мер в финансовом секторе. Планомерно расширяется круг преференциальных внешнеторговых партнёров «пятёрки». Сегодня состоялась, как я уже упомянул вначале, церемония подписания соглашения о свободной торговле между Евразэс и Ираном. Хотел бы поздравить всех нас и присутствующего здесь иранского Министра промышленности и торговли господина Алиабади с тем, что завершена работа над этим стратегическим документом. Исламская Республика Иран является одной из крупнейших экономик Евразийского региона, технологически развитым государством и ключевым звеном южного торгового пути между рынками Евразэс и странами Ближнего Востока и Южной Азии. Поэтому укрепление связей с этой страной принесёт очевидные выгоды как всем участникам нашего объединения, так и самой Исламской Республике Иран. Как известно, действующее с 2019 года временное торговое соглашение Евразэс с Ираном позволило нарастить встречный товарооборот в два раза, хотя охватывало лишь незначительный перечень товарных позиций. В соответствии же с подписанным сегодня соглашением тарифные льготы будут распространены на более чем 85 процентов товарной номенклатуры и свыше 90 процентов объёмов текущей торговли наших стран с Исламской Республикой Иран. Рассчитываем на оперативное проведение всеми государствами-членами соответствующих ратификационных процедур. Напомню, что в настоящее время готовятся важные договорённости и с другими, обладающими большим экономическим потенциалом странами. Речь идёт о преференциальном соглашении между Евразэс и Египтом – одним из наших ключевых партнёров в арабском мире и на Африканском континенте, с которым страны Евразийского союза связывают тесные отношения и интенсивные торгово-экономические контакты. Работа над проектом соглашения о свободной торговле с Египтом находится на весьма продвинутой стадии. И мы, безусловно, заинтересованы в том, чтобы как можно скорее выйти на его подписание. Помимо этого Евразийская комиссия ведёт переговоры с Объединёнными Арабскими Эмиратами и с Индонезией. Формирование зон свободной торговли с этими странами позволит ещё больше нарастить экспортный потенциал Евразэс, увеличить взаимные поставки на рынки дружественных государств и тем самым придаст дополнительный импульс развитию экономик союза, будет укрупнять и будет диверсифицировать наш общий рынок. В целом с ростом авторитета и экономического веса Евразэс всё больше стран и международных организаций выражают заинтересованность в установлении взаимовыгодных контактов с «пятёркой». У нас уже налажено тесное сотрудничество с такими крупными региональными структурами, как Шанхайская организация сотрудничества и Ассоциация государств Юго-Восточной Азии. Реальную отдачу приносит и работа по сопряжению интеграционных процессов по линии Евразэс и китайской инициативы «Один пояс – один путь». Возвращаясь к сотрудничеству непосредственно в рамках Евразэс, хотел бы акцентировать, что целый ряд важных решений в текущем году был принят в сферах промышленной кооперации, локализации производств, по углублению сотрудничества в области сельского хозяйства и продовольственной безопасности. Напомню, в частности, что на майском саммите Евразэс в Москве мы одобрили запуск специального механизма финансирования, предусматривающего особые льготы для экономических проектов с участием трёх и более стран – участниц союза. В нынешнем году также утверждены правила взаимной торговли электроэнергией на общем рынке и начал свою работу Совет руководителей органов государств Евразэс в сфере энергетики. По итогам нашего заседания мы утвердим решение о наделении этого Совета дополнительными контрольными полномочиям. Продолжается интенсивная работа по развитию единой транспортной системы Евразийского союза, включая международный коридор «Север–Юг». В этом смысле опять же возвращаюсь к нашему сотрудничеству с Исламской Республикой Иран, за которой здесь ключевые позиции. Активизировалось сотрудничество в сфере науки и техники, последовательно укрепляется технологический суверенитет государств Евразэс. Общими усилиями наших стран продвигается цифровая повестка, в том числе создана и успешно развивается интеграционная информационная система, разработаны и применяются единые стандарты обмена данными и правила цифровой коммерции. Ещё одним шагом вперёд на этом направлении станет подписание нами сегодня протокола о внесении изменений в Договор о Таможенном кодексе Евразэс в части регулирования внешней электронной торговли. Естественно, повестка нынешнего заседания Высшего совета включает и другие важные вопросы интеграционного взаимодействия, в их числе координация макроэкономической политики, снятие остающихся ограничений и барьеров во взаимной торговле, совершенствование антидемпинговых механизмов, развитие общего рынка услуг, сближение правового регулирования в сфере естественных монополий. Соответствующие договорённости уже согласованы и будут оформлены сегодня нашими решениями. Дорогие друзья! С 1 января Россия передаёт председательские функции в Евразэс Армении. Я хотел бы пожелать успехов нашим армянским коллегам и друзьям. Разумеется, окажем им всю необходимую помощь. Как мы уже не раз отмечали, в будущем году исполняется десять лет заключению основополагающего договора в Евразэс. И мы сейчас в узком составе договорились, учитывая, что это юбилейное мероприятие, все согласились с моим предложением провести в мае 2024 года саммит, посвящённый этому юбилею, в Москве. Этот саммит откроет новое десятилетие тесной совместной работы по углублению интеграции, повышению благосостояния и качества жизни граждан наших стран. Чёткие ориентиры на этот счёт определены принимаемой сегодня долгосрочной декларацией о дальнейшем развитии экономических процессов в рамках Евразийского экономического союза до 2030 года и на период до 2045-го. И ещё хотел добавить: к нашему заседанию подготовлены проекты решений об обновлении состава Коллегии Евразийской экономической комиссии и Суда Евразэс. Хочу, пользуясь случаем, поблагодарить всех действующих членов Коллегии, судей и особенно Председателя Коллегии Михаила Владимировича Мясниковича за весомый вклад в развитие Евразийского экономического союза. Он действительно многое сделал, чтобы комиссия работала ритмично, эффективно. Также хотел бы поприветствовать заступающего с 1 февраля 2024 года на пост главы Коллегии господина Сагинтаева – мы его очень хорошо знаем, – который уже работал членом ЕЭК и, уверен, энергично и без раскачки примется за свои новые обязанности. Он работал и в Администрации Президента Казахстана и был Премьер-министром Казахстана. Конечно, желаю успехов всему новому составу Коллегии Евразийской комиссии и Суда Евразэс. Позвольте передать слово Николу Воваевичу Пашиняну, а затем выступят другие участники саммита. Кроме того, мы просмотрим видеообращение Президента Республики Куба Мигеля Диаса-Канеля Бермудеса как главы государства – наблюдателя при Евразэс. После чего заслушаем доклад Михаила Владимировича Мясниковича и подпишем и утвердим подготовленные проекты. Благодарю вас за внимание. | I28: http://www.kremlin.ru/events/president/transcripts/73128 | J28: 34 | K28: 0 | L28: 8 | M28: 1 | N28: 0 | O28: 27 | P28: 0
A29: Россия | B29: 2024 | C29: 8 мая | D29: в расширенном составе | E29: Путин | F29: заседание ВЕЭС | G29: Москва | H29: В.Путин: Уважаемые коллеги! Мы договорились, что я начинаю как принимающая сторона. Хотел бы проинформировать всех, кто присоединился к нашей работе, что только что мы провели заседание Высшего Евразийского экономического совета в узком составе, обменялись мнениями по актуальным темам деятельности нашего объединения, приняли решения, касающиеся дальнейшего углубления интеграционного сотрудничества. Хотел бы поприветствовать присоединившихся к заседанию в расширенном составе глав государств – наблюдателей при Евразэс: уважаемых президентов Узбекистана, Шавката Миромоновича Мирзиёева, и Кубы – Мигеля Диас-Канеля Бермудеса. Наша сегодняшняя встреча приурочена к 10-летней годовщине подписания Договора о создании Евразийского экономического союза. Это действительно основополагающий документ, руководствуясь которым страны – участницы объединения совместно проделали масштабную работу по углублению евразийской интеграции, построению общего рынка и формированию уникальной наднациональной системы экономического регулирования. Благодаря ликвидации множества торговых и административных барьеров обеспечена высокая степень свободы перемещения товаров. Страны «пятёрки» перешли на единые технические, санитарные, ветеринарные и фитосанитарные нормы и стандарты. Евразийский союз показал свою эффективность перед лицом новых вызовов, в том числе связанных с проводимой некоторыми странами политикой санкций и демонтажа многих базовых устоев международной торговли. Мы постоянно ведём тонкую настройку институтов и механизмов Евразэс, что позволяет адаптироваться к изменениям и динамично развиваться, несмотря на кризисные явления в глобальной экономике. Осязаемых результатов удалось достичь в создании благоприятного инвестиционного климата на пространстве Евразэс. Этому способствовали совместные решения по защите капиталовложений, поддержки бизнеса и гарантиям прав предпринимателей. Многое сделано и продолжает делаться для продвижения промышленной кооперации, импортозамещения и укрепления технологического суверенитета государств – участников объединения. В частности, в прошлом году по инициативе российского председательства был запущен механизм бюджетного финансирования наукоёмких проектов, осуществляемых предприятиями из стран Евразэс. Большое внимание в Евразийском союзе неизменно уделяется вопросам продовольственной безопасности, развитию агропромышленного комплекса наших государств. Общими усилиями удалось успешно решить задачу самостоятельного, бесперебойного снабжения внутреннего рынка продуктами питания и жизненно необходимыми видами сельхозпродукции. Из года в год расширяется партнёрство между странами объединения в сфере транспорта и логистики, хорошими темпами растут объёмы взаимных грузоперевозок, чему заметно помогало дополнительное обустройство и увеличение пропускной способности пограничных переходов между нашими государствами. Отмечу слаженное взаимодействие участников Евразэс по выстраиванию единой транспортной системы, в активную фазу вошла работа по проекту крупнейшего международного коридора «Север – Юг», который обеспечит прямой выход продукции наших стран к портам на побережье Персидского залива и Индийского океана. Важно, что в реализации транспортных и инфраструктурных проектов по линии Евразэс нами задействуются самые современные технические средства. Для отслеживания, контроля и безопасности грузоперевозок применяются высокотехнологичные навигационные пломбы, широко внедряются электронные товаросопроводительные документы и другие цифровые решения. В целом цифровизация стала одним из приоритетов интеграционной повестки. В рамках Евразэс успешно развивается единая информационная система, аккумулирующая сведения о внешнеэкономической деятельности. Разработаны и применяются унифицированные стандарты обмена электронными данными, действуют согласованные правила цифровой коммерции. Повысить эффективность общего рынка и сделать бизнес-процессы ещё более быстрыми и удобными для предпринимателей и потребителей помогло бы взаимное признание используемых в странах Евразэс электронных подписей. Новым и весьма перспективным направлением представляется взаимодействие по защите окружающей среды и борьбе с климатическими изменениями. На уровне экспертов началась выработка единых подходов к решению актуальных задач в этой сфере. Уважаемые коллеги! Как не раз подчёркивалось, Евразийский экономический союз и вся наша интеграционная деятельность привлекает внимание всё большего числа международных игроков. Заинтересованность в развитии связей с нашим объединением проявляют многие иностранные государства и крупные региональные структуры, такие как Содружество Независимых Государств, Шанхайская организация сотрудничества и Ассоциация государств Юго-Восточной Азии. Планомерно расширяется и круг преференциальных внешнеторговых партнёров Евразэс. Эффективно реализуется торговое соглашение с Китайской Народной Республикой. Реальную отдачу приносит работа по сопряжению интеграционных процессов по линии Евразийского союза и китайской инициативы «Один пояс, один путь». Договорённости о либерализации торговли действуют также с Сербией, Ираном, Вьетнамом. На стадии подготовки – соглашения с такими обладающими большим экономическим потенциалом странами, как Египет, Индонезия, Объединённые Арабские Эмираты. К сегодняшнему заседанию подготовлен проект решения о начале переговоров о заключении временного торгового соглашения с Монголией, с которой страны Евразэс связывают тесные добрососедские отношения и интенсивные торгово-экономические контакты. Нам предстоит утвердить и целый ряд других важных решений, а значит, нынешнее юбилейное заседание Высшего Евразийского экономического совета – это не только подведение итогов совместной работы за прошедшее десятилетие, но и ещё один конкретный шаг по пути углубления интеграции. Напомню в этой связи, что в декабре прошлого года в Санкт-Петербурге мы определили перспективы развития нашего объединения до 2030 года и на период до 2045-го, приняли соответствующую декларацию, которая теперь подкрепляется содержательными, практическими договорённостями. В заключение хотел бы ещё раз поблагодарить всех участников этой встречи за тесное сотрудничество и взаимную поддержку. Уверен, действуя и далее сообща и слаженно, мы добьёмся новых весомых результатов в развитии Евразийского союза и всех наших государств. Позвольте передать слово Премьер-министру Армении Николу Воваевичу Пашиняну, который будет вести наше заседание как председатель Высшего Евразийского экономического совета в текущем году. Спасибо большое. | I29: http://www.kremlin.ru/events/president/transcripts/73992 | J29: 20 | K29: 1 | L29: 6 | M29: 1 | N29: 0 | O29: 14 | P29: 0
A30: Россия | B30: 2024 | C30: 26 декабря | D30: в узком составе | E30: Путин | F30: заседание ВЕЭС | G30: Ленинградская область | H30: В.Путин: Никол Владимирович должен быть на связи. Добрый день. Я, с Вашего позволения, скажу несколько вступительных слов, а потом Вам как председателю передам слово. Уважаемые коллеги! Рад всех вас приветствовать на заседании Высшего Евразийского экономического совета. Сегодня по традиции подведём итоги уходящего года, рассмотрим целый ряд подготовленных для утверждения Советом новых, важных решений, направленных на дальнейшее углубление сотрудничества в рамках Евразэс в самых разных сферах. Разумеется, обсудим и текущие вопросы интеграционного строительства, а также наметим планы на перспективу. Договору об учреждении Евразийского экономического союза в нынешнем году исполняется 10 лет, и этой юбилейной дате было посвящено заседание Высшего Евразийского экономического совета в мае в Москве. Наше объединение утвердилось в качестве одного из самостоятельных и самодостаточных центров формирующегося многополярного мира и продолжает динамично развиваться. Деятельность Евразийского союза способствует расширению торговли и инвестиционных обменов, наращиванию деловых контактов, углублению кооперационных связей, а главное, интеграционное взаимодействие приносит реальную выгоду каждому из участников нашего объединения, на деле помогает обеспечивать стабильный, устойчивый рост как экономик государств «пятёрки», так и Евразийского региона в целом, ведёт к повышению качества жизни и благосостояния граждан наших стран. Подчеркну, Россия высоко ценит взаимовыгодное многоплановое сотрудничество с партнёрами по Евразэс, и мы искренне заинтересованы в активизации совместной работы по всестороннему укреплению нашего интеграционного объединения. Убеждён, что все присутствующие коллеги разделяют такой настрой, поэтому рассчитываю, что наше заседание будет продуктивным и по-настоящему деловым. И, как я уже сказал, в самом начале, после приветственных слов передаю ведение нашего сегодняшнего мероприятия Премьер-министру Республики Армения Николу Воваевичу Пашиняну, который по видеосвязи с нами и как действующий председатель Высшего Евразийского экономического совета будет вести наше заседание. Пожалуйста, Николай Владимирович. Благодарю за внимание. | I30: http://www.kremlin.ru/events/president/news/75948 | J30: 8 | K30: 0 | L30: 0 | M30: 0 | N30: 0 | O30: 5 | P30: 0
A31: Россия | B31: 2025 | C31: 27 июня | D31: ключевые итоги*** | E31: Путин | F31: заседание ВЕЭС | G31: Минск | H31: Развитие сотрудничества в объединении не может не радовать, темпы роста экономик союза выше среднемировых: более 4% против 3,3%. Следующая встреча глав государств ЕАЭС пройдет в Санкт-Петербурге перед Новым годом. Участники саммита в Минске обсуждали санкции только вскользь. Уровень инвестиций в России растет, несмотря на известные сложности. | I31: https://ria.ru/20250627/putin-2025893527.html
A32: Россия | B32: 2025 | C32: 21 декабря | D32: в расширенном составе | E32: Путин | F32: заседание ВЕЭС | G32: Санкт-Петербург | H32: дорогие друзья. как отметили выступившие коллеги, наше сотрудничество в рамках евразийского экономического союза развивается весьма успешно. 00:11 на деле способствует экономическому росту стран- участниц, повышшению доходов бизнеса, а главное- улучшению качества жизни и благосостояния людей. 00:22 так, в текущем году наши экономики демонстрируют уверенную позитивную динамику, растет совокупный ввп. 00:31 и, конечно, чемпионом, я думаю, у нас является кыргызстан с таким заметным ростом десять с лишним процентов валового внутреннего продукта. 00:41 конечно, это очень хороший показатель. мы поздравляем и президента кыргызстана, и всю его команду с этим результатом. 00:52 при этом, что касается нашего союза, совокупный суммарный объем сельхозпродукции. 00:58 скажем, производства сельхозпродукции вырос на два с лишним процентов, розничная торговля- на три, строительства- на четыре и семь. 01:06 доля энергетического экспорта из россии в страны евразэс в этом году выросла почти на двадцать процентов- до тридцати двух миллиардов долларов. 01:16 из совокупного товарооборота- семьдесят три миллиарда долларов за десять месяцев. 01:22 в евразийском союзе налажена устойчивая и независимая от внешнего влияния платежная инфраструктура. 01:29 причем практически все взаиморасчеты выполняются в национальных валютах. 01:35 их доля в коммерческих операциях между государствами евразэс составляет девяносто три процента. 01:42 особо отмечу, что нами реализована рассчитанная на пять лет стратегия евразийской экономической интеграции. 01:51 как результат, устранены многие торговые барьеры, гармонизированы нетарифные регулирования и административные процедуры, улучшена координация в сфере таможенного, таможенной и налоговой политики, запущен механизм поддержки кооперационных проектов. 02:10 дальнейшая интеграционная работа должна выстраиваться на основе одобренной ранее декларации евразийский экономический путь наперед до две тысячи сорок пятого года и в ее развитие сегодня будет утверждена дорожная карта. 02:25 кроме того, на рассмотрении высшего совета вынесен ряд важнейших интеграционных решений. 02:31 они касаются проведения согласованной макроэкономической политики, повышения эффективности технического и ветеринарно- санитарного надзора, либерализации условий сотрудничества в строительном секторе. 02:47 отдельно упомянул проект распоряжения о дальнейших шагах по формированию в евразийском союзе общего финансового рынка. 02:54 речь идет об одном из ключевых направлений интеграционной повестки- о том, чтобы облегчить доступ наших инвесторов к ценным бумагам и фондовым биржам на всем пространстве евразэс, создать оптимальные условия для допуска бизнеса и предприятий кредитным средствам и другим банковским продуктам, а также услугам страхования. 03:20 напомню в этом контексте, что в рамках нашей организации учреждена и действует евразийская перестраховочная компания, которая обеспечена солидным капиталом и призвана поддерживать торговые сделки между нашими странами, и ее возможности нужно задействовать полнее. 03:40 еще один интеграционный приоритет- укрепления транспортного каркаса евразэс. 03:45 со следующего года в евразийском союзе начнется постепенное внедрение навигационных пломб, которые позволяют отслеживать перевозки грузов по территории стран участия в режиме реального времени, гарантируя максимальную прозрачность логистических операций. 04:05 также предлагаем партнерам по евросоюз присмотреться и к опыту использования в рамках союзного государства россии и белоруссии электронных транспортных накладных. 04:15 их применение заметно упростило грузоперевозки, помогло снизить издержки при транспортировке и досмотре товаров. 04:24 многообещающей сферой интеграции является туризм. принимаемая нами сегодня концепция развития сотрудничества на этом направлении содержит конкретные ориентиры по увеличению туристических потоков внутри евразийского союза. 04:40 планируется создание новых трансграничных и международных туристических маршрутов. 04:46 уважаемые коллеги. все больше стран и многосторонних структур выражают готовность выстраивать взаимоотношения с нашим объединением продолжает расширяться круг преференциальных внешнеторговых партнеров евразэс. 05:02 коллеги уже говорили, я позволю себе повторить: в нынешнем году вступило в силу договоренность о свободной торговле с ираном, заключены новые торговые соглашения с объединенными арабскими эмиратами, с монголией. 05:16 сегодня состоится подписание аналогичного документа между евразэс и индонезией. 05:22 оно установит режим свободной торговли в отношении свыше девяноста процентов товарной номенклатуры и порядка девяносто пяти процентов взаимного товарооборота. 05:34 тем самым откроются хорошие перспективы для углубления многопланового взаимодействия стран пятерки с одной из крупнейших и наиболее динамично развивающихся экономик азии и всего мира. 05:50 значительно улучшаться условия доступа произведенные в евразийском союзе продукции на емкие рынки азиатско- тихоокеанского региона в целом общее экономическое пространство евразэс. 06:04 уже заключенные нами преференциальные соглашения, зона свободной торговли снг вместе охватывают огромный рынок в семьсот тридцать миллионов потребителей. 06:17 при этом в проработке находится еще и преференциальное соглашение с индией- страной, проводящей суверенную внешнюю политику, надежным партнером с рынком на полтора миллиарда человек и около четырех триллионов долларов ввп. 06:39 первый раунд консультации по тексту соглашения прошел месяц назад. 06:43 отмечу, что в ходе нашего недавнего государственного визита в нью- дели индийская сторона выразила готовность активизировать процесс согласования этого важного документа. 06:55 сегодня на рассмотрение высшего совета также вынесено решение о начале переговоров с узбекистаном по соглашению об обмене информацией о товарах и транспортных средствах, перемещаемых через таможенные границы евразийского союза. 07:10 это вполне естественный шаг, ведь все государства евразэс поддерживают с узбекистанцами друзьями самые тесные добрососедские отношения и интенсивные торгово- экономические контакты. 07:23 и в заключение хотел бы, пользуясь случаем, и выразить признательность александра григорьевича лукашенко и всем белорусским нашим друзьям, коллегам за конструктивный и инициативный подход к выполнению председательских функций в евразэс и хорошую организацию нашей совместной работы в уходящем году. 07:41 и, конечно, желаю успеховкаеву, всем нашим казахстанским коллегам, заступающим с первого января на председательскую вахту вразэс. 07:53 безусловно, готовы. будем оказывать все необходимое, желаемое содействие. 07:58 ну и, конечно же, как и другие коллеги, выступавшие до меня, поздравляю вас всех с наступающим новым годом. | I32: https://yandex.ru/video/preview/9502122485974629429 | J32: 19 | K32: 1 | L32: 11 | M32: 0 | N32: 0 | O32: 11 | P32: 0
E33: Сумма по РФ | J33: =SUM(J4:J32) -> 412 | K33: =SUM(K4:K32) -> 7 | L33: =SUM(L4:L32) -> 203 | M33: =SUM(M4:M32) -> 13 | N33: =SUM(N4:N32) -> 0 | O33: =SUM(O4:O32) -> 340 | P33: =SUM(P4:P32) -> 9
A34: Беларусь | B34: 2014 | C34: 23 декабря | E34: Лукашенко | F34: заседание ВЕЭС | G34: Москва | H34: Александр Лукашенко признал, что переговоры на заседании Высшего Евразийского экономического совета были непростыми. По его мнению, это естественно, поскольку спектр вопросов функционирования ЕАЭС, старт которому будет дан уже через 8 дней, весьма широк, а поставленные задачи амбициозны. "В результате открытого и, скажу прямо, непростого разговора мы постарались найти точки соприкосновения и развязки по наиболее животрепещущим темам, в том числе по тем, которые в последнее время не сходят со страниц средств массовой информации и обрастают, как это часто бывает, различными домыслами. Сам факт того, что на уровень президентов был вынесен 21 вопрос, притом по экономическим проблемам, говорит о напряженной работе, которая ведется на интеграционной площадке, о масштабе решаемых сегодня задач", - отметил Глава белорусского государства. Президент Беларуси считает, что плюсы Союза очевидны, а потому остановился на проблемных моментах. В частности, нерешенным остается вопрос свободного движения товаров, которого в полном объеме как не было, так и нет. Кроме того, до сих пор между российской и белорусской сторонами не обеспечено взаимное предоставление наиболее благоприятных национальных режимов доступа к государственным закупкам, хотя сделать это следовало еще с 1 января 2012 года. "Вы - журналисты - хорошо знаете, что происходило на границе России с Беларусью с августа этого года. Сами подробно информировали о предмете прошедших в ноябре-декабре в наших столицах многочисленных двусторонних консультаций на разных уровнях. Правда, информировали об одном и том же по-разному", - сказал Глава белорусского государства. "Вот и ответьте на вопрос: есть ли на сегодняшний день между нами реальная либерализация условий торговли?" - сказал Президент Беларуси. Александр Лукашенко обратил внимание и на другую сторону медали в существующих разногласиях, которые, как надеется Президент Беларуси, временны. "Россельхознадзор ввел ограничения на поставку продукции белорусских предприятий в Российскую Федерацию. Более того, вопреки всем международным нормам нам запретили транзит товаров с белорусской территории! Это все сделано в одностороннем порядке без каких-либо консультаций, минуя Евразийскую экономическую комиссию!" - отметил Глава белорусского государства. "Более того, как стало известно в результате сегодняшних переговоров с Владимиром Владимировичем, и без его согласия", - добавил белорусский лидер. "Отсюда вывод: четкого механизма взаимодействия и контроля в рамках единого таможенного пространства пока в полном объеме нет. А самое грустное - от ЕЭК не просматривается никакого стремления хоть как-нибудь изменить ситуацию, - сказал Глава белорусского государства. - Представляется, что комиссия фактически дистанцировалась от решения действительно чувствительных проблем". Александр Лукашенко констатировал, что отношения внутри Таможенного союза и ЕЭП проходят через серьезнейшие испытания. "Есть вопросы, однозначных ответов на которые, к сожалению, пока нет. А время их уже настоятельно требует", - отметил Президент Беларуси. В январе-сентябре 2014 года объем взаимной торговли государств - членов Таможенного союза и ЕЭП сложился на уровне $42,8 млрд, что составляет лишь 89,5% к аналогичному периоду прошлого года. "Промедление с принятием на данном этапе жизненно важных решений может обернуться не только потерей динамики объединительных процессов, но и откатом назад, чего народы наших государств современным политикам не простят, особенно учитывая нашу практику работы в СНГ. Второго СНГ народы не потерпят", - сказал белорусский лидер. Любой союз должен работать на благосостояние своих граждан, подчеркнул Александр Лукашенко. "Сегодня каждой из сторон исключительно важно выдержать разумный баланс между национальными приоритетами и межгосударственными обязательствами. А всем вместе - добиться желаемой эффективности от Евразийской экономической комиссии. Потенциал стран - членов Союза велик. Сближение лишь умножает наши силы, - считает Президент Беларуси. - А значит, движение, как сейчас модно говорить, на интеграционном треке должно быть продолжено. Другого пути у нас нет". Александр Лукашенко также подчеркнул готовность к продолжению равноправного взаимовыгодного диалога по любым вопросам и выразил уверенность, что так же будет выражена и позиция партнеров. https://president.gov.by/ru/events/rabochij-vizit-v-rossijskuju-federatsiju-10519 | I34: https://president.gov.by/ru/events/rabochij-vizit-v-rossijskuju-federatsiju-10519 | J34: 3 | K34: 1 | L34: 1 | M34: 1 | N34: 0 | O34: 3 | P34: 0
